Workbook

Sheet Cover
B2: TWB Designs — Demilitarization & Global Secure Destruction Platform
B3: Financial model · 10-year plan (2026–2036) · USD millions · Investor package build of 1 September 2026
B5: How this model is built
B6: Every figure in the deck and the memo ties to a cell on the Outputs tab. Inputs live only on the Inputs, Baseline, Market and Acquisitions tabs; every other tab is formulas.
B8: Colour legend
B9: Blue text on yellow = hard-coded input or scenario lever (edit these). Black = formula. Green = link to another tab. Sage band = section header.
B10: Every input carries a cell comment saying whether it is SOURCED (with citation), COMPANY-PROVIDED, an ASSUMPTION (our construction), or a PLACEHOLDER awaiting company data.
B12: Scenario selector
B13: Inputs!C6 = 1 Downside · 2 Base · 3 Upside. Every scenario-driven input reads from its Downside/Base/Upside columns via CHOOSE, so the whole workbook re-runs live. The Scenarios tab also holds a snapshot of all three cases taken at build time.
B15: Tabs
B16: Inputs — every assumption and scenario lever, grouped: organic drivers, margins, corporate, acquisitions programme, capital, valuation.
B17: Baseline — FY2023–FY2025 actuals (compiled, unaudited, CAD → USD at Bank of Canada annual averages) and the FY2026 placeholder.
... B29: Headline (live, base case unless the selector is changed)
B30: Revenue — Year 5 (2031) | C30: =Outputs!$C$11
B31: Revenue — Year 10 (2036) | C31: =Outputs!$C$15
B32: Adjusted EBITDA — Year 10 | C32: =Outputs!$C$21
B33: Capital required 2026–31 (Phases 1–3) | C33: =Outputs!$C$29+Outputs!$C$30+Outputs!$C$31
B34: Acquisitions in plan | C34: =Outputs!$C$24
B35: Returns case — MOIC / IRR at Year-7 exit | C35: =TEXT(Outputs!$C$63,"0.0x")&" / "&TEXT(Outputs!$C$64,"0%")

Sheet Inputs
B2: Inputs & scenario levers
B3: Blue on yellow = edit. Column C is the LIVE value used by the model; D/E/F hold Downside / Base / Upside where a lever is scenario-driven.
B6: SCENARIO SELECTOR (1 = Downside, 2 = Base, 3 = Upside) | C6: 2
B7: Active scenario | C7: =CHOOSE($C$6,"Downside","Base","Upside")
B9: Lever | C9: Live | D9: Downside | E9: Base | F9: Upside | G9: Basis / source
B10: A. Organic drivers — custody destruction services (eMACS fleet)
B11: CAD per USD — Bank of Canada annual average 2025 | C11: 1.3978 | G11: SOURCED: Bank of Canada annual average exchange rates (FXAUSDCAD) 2025 = 1.3978; 2024 = 1.3698; 2023 = 1.3497.
B12: Revenue per deployed eMACS unit-year (USD M) | C12: =CHOOSE($C$6,D12,E12,F12) | D12: 0.4 | E12: 0.5 | F12: 0.6 | G12: ASSUMPTION for a fully utilised unit under the platform (US entity, LE + defence + allied demand). Note: FY2025 services revenue was USD 0.52M across the existing fleet, i.e. well below this rate per unit — the plan assumes utilisation rises. Y0 uses the Baseline placeholder, not this rate.
B13: Service price escalation per year | C13: =CHOOSE($C$6,D13,E13,F13) | D13: 0.02 | E13: 0.03 | F13: 0.04 | G13: ASSUMPTION.
B14: First-year utilisation of a newly deployed unit | C14: =CHOOSE($C$6,D14,E14,F14) | D14: 0.4 | E14: 0.5 | F14: 0.6 | G14: ASSUMPTION: a unit added in year t earns this fraction of a full unit-year in t.
B15: Metals recovery contribution — % of custody destruction services revenue | C15: =CHOOSE($C$6,D15,E15,F15) | D15: 0.05 | E15: 0.1 | F15: 0.15 | G15: ASSUMPTION (original model used 14%). Underwritten on LE/commercial/allied work only — in US DoD demil services the Army sells recyclable material itself (10 USC 7690).
B16: eMACS equipment sale price per unit (USD M) | C16: =CHOOSE($C$6,D16,E16,F16) | D16: 0.55 | E16: 0.65 | F16: 0.75 | G16: COMPANY-PROVIDED anchor: FY2024 equipment revenue CAD 863,500 ≈ USD 0.63M (one unit sale). Base 0.65.
B17: Average annual revenue per allied / sovereign programme (USD M) | C17: =CHOOSE($C$6,D17,E17,F17) | D17: 6 | E17: 10 | F17: 15 | G17: ASSUMPTION / PLACEHOLDER. Sovereign design-build-operate-certify programmes; no public comparable — to be hardened in diligence.
B18: Post-conflict / clearance programme revenue at maturity (USD M per programme-year) | C18: =CHOOSE($C$6,D18,E18,F18) | D18: 3 | E18: 5 | F18: 8 | G18: ASSUMPTION. Ukraine EHM need US$27.6bn 2026–35 (RDNA5); tenders are commercial and contestable.
B19: B. Margins (EBITDA contribution by line)
B20: Custody destruction services | C20: =CHOOSE($C$6,D20,E20,F20) | D20: 0.25 | E20: 0.3 | F20: 0.35 | G20: ASSUMPTION anchored to FY2023–25 combined EBITDA margins of 27–43% on a small base; scaled fleet assumed lower.
B21: Equipment sales | C21: =CHOOSE($C$6,D21,E21,F21) | D21: 0.2 | E21: 0.25 | F21: 0.3 | G21: ASSUMPTION.
B22: Allied / sovereign programmes | C22: =CHOOSE($C$6,D22,E22,F22) | D22: 0.12 | E22: 0.15 | F22: 0.18 | G22: ASSUMPTION (engineering / build-operate work).
B23: Post-conflict programmes | C23: =CHOOSE($C$6,D23,E23,F23) | D23: 0.1 | E23: 0.15 | F23: 0.18 | G23: ASSUMPTION.
B24: Metals recovery (contribution after processing & logistics) | C24: =CHOOSE($C$6,D24,E24,F24) | D24: 0.4 | E24: 0.5 | F24: 0.6 | G24: ASSUMPTION.
B25: C. Corporate platform cost (USD M per year, before acquisitions) — Base schedule; scenario scales it
B26: Corporate cost scale factor vs Base schedule | C26: =CHOOSE($C$6,D26,E26,F26) | D26: 0.75 | E26: 1 | F26: 1.15 | G26: ASSUMPTION: Upside carries a heavier platform team earlier.
B27: Incremental platform overhead as % of acquired revenue | C27: =CHOOSE($C$6,D27,E27,F27) | D27: 0.03 | E27: 0.02 | F27: 0.02 | G27: ASSUMPTION: integration/central functions layered on acquired businesses.
B28: D. Acquisition programme levers (deal table on the Acquisitions tab)
B29: Post-acquisition revenue growth of acquired businesses | C29: =CHOOSE($C$6,D29,E29,F29) | D29: 0.06 | E29: 0.12 | F29: 0.18 | G29: ASSUMPTION. Original model 15%.
B30: EBITDA margin uplift on acquired businesses by third year post-close (pts) | C30: =CHOOSE($C$6,D30,E30,F30) | D30: 0 | E30: 0.04 | F30: 0.06 | G30: ASSUMPTION: cross-sell, shared recovery relationships, procurement.
B31: One-off integration cost as % of purchase price | C31: =CHOOSE($C$6,D31,E31,F31) | D31: 0.12 | E31: 0.1 | F31: 0.08 | G31: ASSUMPTION.
B32: Close-year shift applied to every deal (years; +1 = later) | C32: =CHOOSE($C$6,D32,E32,F32) | D32: 1 | E32: 0 | F32: 0 | G32: ASSUMPTION: Downside delays every deal one year. Upside keeps base timing (deal 7 switches on instead).
B33: Pricing basis: 1 = EBITDA multiple (deal table), 2 = revenue multiple (sensitivity) | C33: 1 | G33: Switch to 2 to price every deal at the revenue multiple below (stress test against disclosed sector transactions at 1.5–3.4x revenue).
B34: Revenue multiple used when pricing basis = 2 | C34: 2 | G34: SOURCED band: Cadre–ICOR ~2.3x; Cadre–Alpha Safety ~2.4x; Cadre–Carr's ~1.5x; Rheinmetall–Expal ~3.4x (2021 revenue). 2.0x used as the stress case.
B35: E. Capital & working capital
B36: Fleet capex — cost to build one eMACS unit (USD M) | C36: =CHOOSE($C$6,D36,E36,F36) | D36: 0.45 | E36: 0.4 | F36: 0.4 | G36: PLACEHOLDER: build cost per unit not provided; set below the 0.65 sale price. TOM TO CONFIRM.
B37: Maintenance capex — % of total revenue | C37: =CHOOSE($C$6,D37,E37,F37) | D37: 0.03 | E37: 0.025 | F37: 0.02 | G37: ASSUMPTION.
B38: Working capital — % of incremental revenue | C38: =CHOOSE($C$6,D38,E38,F38) | D38: 0.15 | E38: 0.12 | F38: 0.1 | G38: ASSUMPTION (government receivables).
B39: Development & partnership programme spend scale vs Base schedule | C39: =CHOOSE($C$6,D39,E39,F39) | D39: 0.8 | E39: 1 | F39: 1.3 | G39: ASSUMPTION: calibre-ladder development, certification layer, robotics/university partnerships.
B40: Cash tax rate on positive EBIT (simplified) | C40: =CHOOSE($C$6,D40,E40,F40) | D40: 0.26 | E40: 0.26 | F40: 0.26 | G40: ASSUMPTION: blended Canada/US statutory ~26%; losses carried forward not modelled (conservative).
B41: Depreciation & amortisation — % of revenue (for tax only) | C41: =CHOOSE($C$6,D41,E41,F41) | D41: 0.04 | E41: 0.04 | F41: 0.04 | G41: ASSUMPTION.
B42: F. Valuation & returns
B43: Exit EV/EBITDA multiple (returns case) | C43: =CHOOSE($C$6,D43,E43,F43) | D43: 8 | E43: 10 | F43: 12 | G43: ASSUMPTION bounded by SOURCED comps: KPMG A&D government services ~11.2x (end-2025); Cadre trades 15.3x (Aug 2026); lower-middle-market private 5.5–6.4x (GF Data 2025). 10x base for a scaled platform.
B44: Discount rate — Year-10 DFV bridge | C44: =CHOOSE($C$6,D44,E44,F44) | D44: 0.3 | E44: 0.25 | F44: 0.2 | G44: ASSUMPTION: 25–35% is the venture/growth underwriting band; original model used 20% (too low per teardown).
B45: DFV bridge — low comp multiple (public A&D services) | C45: 11.2 | G45: SOURCED: KPMG Government Technology Solutions H2 2025 — sector EV/EBITDA 11.2x.
B46: DFV bridge — high comp multiple (Cadre Holdings trading multiple) | C46: 15.3 | G46: SOURCED: Cadre Holdings EV/EBITDA 15.25x, stockanalysis.com, 31 Aug 2026. (Private A&D deal median 18.96x per PCE Q2 2026 shown on the Returns tab as an upper reference, not used.)
B47: Year-10 EBITDA margin used in the DFV bridge | C47: ='P&L & Capital'!N24 | G47: LINKED to the operating model (original model hard-coded 20%).
B49: G. Financing — initial raise
B50: Initial raise (Round 1) — amount | C50: 10 | G50: COMPANY-PROVIDED: confirmed by Tom, 2 Sep 2026. This is the round being raised now — a decision input, not derived from the model. The phase ladder and use-of-proceeds below show what it is sized against and how far it reaches.
B52: H. Yearly schedules — three rows per driver (Downside / Base / Upside); LIVE row picks by selector
B53: USD millions unless noted | C53: Input / note | D53: 2026 | E53: 2027 | F53: 2028 | G53: 2029 | H53: 2030 | I53: 2031 | J53: 2032 | K53: 2033 | L53: 2034 | M53: 2035 | N53: 2036
B54: Model year | D54: Y0 | E54: Y1 | F54: Y2 | G54: Y3 | H54: Y4 | I54: Y5 | J54: Y6 | K54: Y7 | L54: Y8 | M54: Y9 | N54: Y10
B55: eMACS units added to the deployed fleet (count; Y0 = units in service today) | C55: PLACEHOLDER Y0 = 2 units in service (TOM TO CONFIRM). Additions are ASSUMPTIONS.
B56: Downside | D56: 2 | E56: 0 | F56: 1 | G56: 1 | H56: 1 | I56: 1 | J56: 1 | K56: 1 | L56: 1 | M56: 1 | N56: 1
B57: Base | D57: 2 | E57: 1 | F57: 2 | G57: 3 | H57: 3 | I57: 3 | J57: 3 | K57: 3 | L57: 3 | M57: 3 | N57: 3
B58: Upside | D58: 2 | E58: 2 | F58: 3 | G58: 4 | H58: 4 | I58: 4 | J58: 4 | K58: 4 | L58: 4 | M58: 4 | N58: 4
B59: LIVE | D59: =CHOOSE($C$6,D56,D57,D58) | E59: =CHOOSE($C$6,E56,E57,E58) | F59: =CHOOSE($C$6,F56,F57,F58) | G59: =CHOOSE($C$6,G56,G57,G58) | H59: =CHOOSE($C$6,H56,H57,H58) | I59: =CHOOSE($C$6,I56,I57,I58) | J59: =CHOOSE($C$6,J56,J57,J58) | K59: =CHOOSE($C$6,K56,K57,K58) | ... N59: =CHOOSE($C$6,N56,N57,N58)
B61: eMACS equipment units sold via agents (count) | C61: ASSUMPTION; history is lumpy (one sale in FY2024).
B62: Downside | D62: 0 | E62: 0 | F62: 1 | G62: 0 | H62: 1 | I62: 1 | J62: 1 | K62: 1 | L62: 1 | M62: 1 | N62: 1
B63: Base | D63: 0 | E63: 1 | F63: 1 | G63: 2 | H63: 2 | I63: 2 | J63: 3 | K63: 3 | L63: 3 | M63: 3 | N63: 3
B64: Upside | D64: 0 | E64: 1 | F64: 2 | G64: 2 | H64: 3 | I64: 3 | J64: 4 | K64: 4 | L64: 4 | M64: 4 | N64: 4
B65: LIVE | D65: =CHOOSE($C$6,D62,D63,D64) | E65: =CHOOSE($C$6,E62,E63,E64) | F65: =CHOOSE($C$6,F62,F63,F64) | G65: =CHOOSE($C$6,G62,G63,G64) | H65: =CHOOSE($C$6,H62,H63,H64) | I65: =CHOOSE($C$6,I62,I63,I64) | J65: =CHOOSE($C$6,J62,J63,J64) | K65: =CHOOSE($C$6,K62,K63,K64) | ... N65: =CHOOSE($C$6,N62,N63,N64)
B67: Allied / sovereign programmes active (count) | C67: ASSUMPTION: Phase 3 offer (design-build-operate-certify) from 2030 in Base.
B68: Downside | D68: 0 | E68: 0 | F68: 0 | G68: 0 | H68: 0 | I68: 0 | J68: 1 | K68: 1 | L68: 2 | M68: 2 | N68: 3
B69: Base | D69: 0 | E69: 0 | F69: 0 | G69: 0 | H69: 1 | I69: 2 | J69: 3 | K69: 4 | L69: 5 | M69: 6 | N69: 8
B70: Upside | D70: 0 | E70: 0 | F70: 0 | G70: 1 | H70: 2 | I70: 3 | J70: 4 | K70: 6 | L70: 8 | M70: 10 | N70: 12
B71: LIVE | D71: =CHOOSE($C$6,D68,D69,D70) | E71: =CHOOSE($C$6,E68,E69,E70) | F71: =CHOOSE($C$6,F68,F69,F70) | G71: =CHOOSE($C$6,G68,G69,G70) | H71: =CHOOSE($C$6,H68,H69,H70) | I71: =CHOOSE($C$6,I68,I69,I70) | J71: =CHOOSE($C$6,J68,J69,J70) | K71: =CHOOSE($C$6,K68,K69,K70) | ... N71: =CHOOSE($C$6,N68,N69,N70)
B73: Post-conflict / clearance programme-years (count, at maturity value) | C73: ASSUMPTION: entered via acquired large-calibre capability and allied partners.
B74: Downside | D74: 0 | E74: 0 | F74: 0 | G74: 0 | H74: 0 | I74: 0 | J74: 1 | K74: 1 | L74: 2 | M74: 2 | N74: 2
B75: Base | D75: 0 | E75: 0 | F75: 0 | G75: 1 | H75: 1 | I75: 2 | J75: 2 | K75: 3 | L75: 3 | M75: 4 | N75: 4
B76: Upside | D76: 0 | E76: 0 | F76: 1 | G76: 1 | H76: 2 | I76: 3 | J76: 4 | K76: 5 | L76: 5 | M76: 6 | N76: 6
B77: LIVE | D77: =CHOOSE($C$6,D74,D75,D76) | E77: =CHOOSE($C$6,E74,E75,E76) | F77: =CHOOSE($C$6,F74,F75,F76) | G77: =CHOOSE($C$6,G74,G75,G76) | H77: =CHOOSE($C$6,H74,H75,H76) | I77: =CHOOSE($C$6,I74,I75,I76) | J77: =CHOOSE($C$6,J74,J75,J76) | K77: =CHOOSE($C$6,K74,K75,K76) | ... N77: =CHOOSE($C$6,N74,N75,N76)
B79: Corporate platform cost — Base schedule (USD M) | C79: ASSUMPTION: leadership, M&A, finance, QHSE/compliance, BD. Scenario applies the scale factor in C.
B80: Downside | D80: 1.2 | E80: 2 | F80: 3 | G80: 4 | H80: 5 | I80: 6 | J80: 7 | K80: 8 | L80: 9 | M80: 10 | N80: 11
B81: Base | D81: 1.2 | E81: 2 | F81: 3 | G81: 4 | H81: 5 | I81: 6 | J81: 7 | K81: 8 | L81: 9 | M81: 10 | N81: 11
B82: Upside | D82: 1.2 | E82: 2 | F82: 3 | G82: 4 | H82: 5 | I82: 6 | J82: 7 | K82: 8 | L82: 9 | M82: 10 | N82: 11
B83: LIVE | D83: =CHOOSE($C$6,D80,D81,D82) | E83: =CHOOSE($C$6,E80,E81,E82) | F83: =CHOOSE($C$6,F80,F81,F82) | G83: =CHOOSE($C$6,G80,G81,G82) | H83: =CHOOSE($C$6,H80,H81,H82) | I83: =CHOOSE($C$6,I80,I81,I82) | J83: =CHOOSE($C$6,J80,J81,J82) | K83: =CHOOSE($C$6,K80,K81,K82) | ... N83: =CHOOSE($C$6,N80,N81,N82)
B85: Development & partnership programmes — Base schedule (USD M) | C85: ASSUMPTION: calibre-ladder development, certification/custody data layer, robotics & university partnerships; scaled by dev_scale.
B86: Downside | D86: 0.3 | E86: 0.8 | F86: 1 | G86: 1.5 | H86: 2 | I86: 2 | J86: 2.5 | K86: 2.5 | L86: 3 | M86: 3 | N86: 3
B87: Base | D87: 0.3 | E87: 0.8 | F87: 1 | G87: 1.5 | H87: 2 | I87: 2 | J87: 2.5 | K87: 2.5 | L87: 3 | M87: 3 | N87: 3
B88: Upside | D88: 0.3 | E88: 0.8 | F88: 1 | G88: 1.5 | H88: 2 | I88: 2 | J88: 2.5 | K88: 2.5 | L88: 3 | M88: 3 | N88: 3
B89: LIVE | D89: =CHOOSE($C$6,D86,D87,D88) | E89: =CHOOSE($C$6,E86,E87,E88) | F89: =CHOOSE($C$6,F86,F87,F88) | G89: =CHOOSE($C$6,G86,G87,G88) | H89: =CHOOSE($C$6,H86,H87,H88) | I89: =CHOOSE($C$6,I86,I87,I88) | J89: =CHOOSE($C$6,J86,J87,J88) | K89: =CHOOSE($C$6,K86,K87,K88) | ... N89: =CHOOSE($C$6,N86,N87,N88)
B91: I. Adjusted EBITDA margin — target override (Y1–Y10; replaces bottom-up corporate-cost build) | C91: ASSUMPTION (Tom, 3 Sep 2026): blended Adjusted EBITDA margin reaches 30% by Year 5, then grows to 35% by Year 10. Implemented as a direct margin target; corporate platform cost (P&L & Capital row 19) is solved residually each year so Adjusted EBITDA / Revenue equals this target exactly. Year 0 is unaffected (pre-scale organic base).
B92: Downside | E92: -0.05 | F92: 0.025 | G92: 0.1 | H92: 0.175 | I92: 0.25 | J92: 0.26 | K92: 0.27 | L92: 0.28 | M92: 0.29 | N92: 0.3
B93: Base | E93: 0 | F93: 0.075 | G93: 0.15 | H93: 0.225 | I93: 0.3 | J93: 0.31 | K93: 0.32 | L93: 0.33 | M93: 0.34 | N93: 0.35
B94: Upside | E94: 0.05 | F94: 0.125 | G94: 0.2 | H94: 0.275 | I94: 0.35 | J94: 0.36 | K94: 0.37 | L94: 0.38 | M94: 0.39 | N94: 0.4
B95: LIVE | E95: =CHOOSE($C$6,E92,E93,E94) | F95: =CHOOSE($C$6,F92,F93,F94) | G95: =CHOOSE($C$6,G92,G93,G94) | H95: =CHOOSE($C$6,H92,H93,H94) | I95: =CHOOSE($C$6,I92,I93,I94) | J95: =CHOOSE($C$6,J92,J93,J94) | K95: =CHOOSE($C$6,K92,K93,K94) | L95: =CHOOSE($C$6,L92,L93,L94) | ... N95: =CHOOSE($C$6,N92,N93,N94)

Sheet Baseline
B2: Baseline — actual financials (compiled, unaudited) and the FY2026 placeholder
B3: Source: compiled financial statements for TWB Designs Inc. and Canadian Ammunition Disposal Services Inc. (CADS), FY2023–FY2025, as reproduced in the August 2026 supporting memo. CAD converted at Bank of Canada annual averages.
B6: Combined income statement (CAD) | C6: CAD | D6: FY2023 | E6: FY2024 | F6: FY2025 | G6: Note
B7: CADS revenue (destruction services) | D7: 901305 | E7: 847761 | F7: 720044 | G7: COMPANY-PROVIDED.
B8: TWB Designs revenue (equipment sales, lumpy) | D8: 64425 | E8: 863500 | F8: 142812 | G8: COMPANY-PROVIDED. FY2024 includes one equipment sale.
B9: Combined revenue | D9: =D7+D8 | E9: =E7+E8 | F9: =F7+F8 | G9: Sum. Note: CADS pays TWB a CAD 60K/yr intercompany fee; simple sum overstates consolidated revenue by ~60K.
B10: Combined gross profit | D10: 759474 | E10: 760306 | F10: 569099 | G10: COMPANY-PROVIDED.
B11: Combined EBITDA (approx.) | D11: 419000 | E11: 492000 | F11: 235000 | G11: COMPANY-PROVIDED (approximate). FY2024 net income included a one-time CAD 265,874 FX gain.
B12: Combined net income | D12: 337094 | E12: 589471 | F12: 125174 | G12: COMPANY-PROVIDED.
B13: EBITDA margin | D13: =IF(D9=0,0,D11/D9) | E13: =IF(E9=0,0,E11/E9) | F13: =IF(F9=0,0,F11/F9)
B15: Bank of Canada annual average CAD per USD | D15: 1.3497 | E15: 1.3698 | F15: 1.3978 | G15: https://www.bankofcanada.ca/rates/exchange/annual-average-exchange-rates/
B17: Combined income statement (USD M) | C17: USD M | D17: FY2023 | E17: FY2024 | F17: FY2025
B18: Destruction services revenue | D18: =D7/D$15/1000000 | E18: =E7/E$15/1000000 | F18: =F7/F$15/1000000
B19: Equipment sales revenue | D19: =D8/D$15/1000000 | E19: =E8/E$15/1000000 | F19: =F8/F$15/1000000
B20: Combined revenue | D20: =D9/D$15/1000000 | E20: =E9/E$15/1000000 | F20: =F9/F$15/1000000
B21: Combined EBITDA | D21: =D11/D$15/1000000 | E21: =E11/E$15/1000000 | F21: =F11/F$15/1000000
B23: Balance sheet at 31 Dec 2025 (CAD) | D23: CADS | E23: TWB | F23: Combined
B24: Cash | D24: 139667 | E24: 59431 | F24: =D24+E24
B25: Total assets | D25: 509193 | E25: 118825 | F25: =D25+E25
B26: Total liabilities | D26: 42890 | E26: 4799 | F26: =D26+E26
B27: Book value (equity) | D27: 466303 | E27: 114026 | F27: =D27+E27
B28: Interest-bearing debt | F28: 0
B30: FY2026 starting point used by the model (USD M)
B31: FY2026 destruction-services revenue estimate — PLACEHOLDER | D31: =F18 | G31: Overwrite with the FY2026 estimate when available (Tom, 1 Sep 2026: leave as a marked placeholder).
B32: FY2026 equipment sales — PLACEHOLDER (units, valued at Inputs sale price) | D32: 0
B33: Opening cash (USD M, 31 Dec 2025) | D33: =F21/F15/1000000
B35: Note: the deck does not present current revenue or EBITDA (per the brief). The memo discloses this baseline in full. These are compilation engagements — no assurance is provided; diligence requires bank statements, HST filings, AR ageing and customer contracts.

Sheet Market
B2: Market construction — TAM / SAM / SOM (USD M per year, 2026)
B3: "Our construction": no analyst covers munitions end-of-life. Every layer states whether it is SOURCED or an ASSUMPTION. SOM is the model's own Year-5 revenue, not a top-down share.
B6: Layer | C6: Anchor (USD M) | D6: Factor | E6: Included (USD M) | F6: Growth /yr | G6: Basis
B7: 1a. US Army conventional munitions demil budget line (4099EP1700), FY2026 | C7: 155.05 | D7: 1 | E7: =C7*D7 | F7: 0.02 | G7: SOURCED: FY2027 Army Procurement of Ammunition J-book — $155.050M FY2026, $161.179M FY2027. Growth ASSUMPTION 2%.
B8: 1b. Other US DoD / federal destruction, disposal and demil services outside the Army line (services, other services, DLA, ranges) | C8: 150 | D8: 1 | E8: =C8*D8 | F8: 0.03 | G8: ASSUMPTION / PLACEHOLDER: no consolidated public figure. Sized at ~1x the Army line. Hardening needed in diligence.
B9: 1c. Allied national demil & stockpile-destruction budgets (NATO Europe, Canada, Australia, Israel, partners) | C9: 450 | D9: 1 | E9: =C9*D9 | F9: 0.05 | G9: ASSUMPTION: ~3x the US Army line across ~30 allied MoDs; NATO identifies $145bn of munitions requirements (Mar 2026) and Europe doubled spending 2016–25 (SIPRI) — stockpile turnover follows. No published aggregate.
B10: 1d. Law-enforcement, civil and commercial secure destruction (ammunition, seized property) — North America + Europe | C10: 100 | D10: 1 | E10: =C10*D10 | F10: 0.03 | G10: ASSUMPTION: thousands of agencies with recurring disposal needs; no published aggregate. UN ran two mobile-destruction procurements in 2025 (UNGM).
B11: 2. Military & LE EOD equipment and services market, global | C11: 8550 | D11: 0.3 | E11: =C11*D11 | F11: 0.03 | G11: SOURCED size: Global Growth Insights $8.55bn (2025), 3.03% CAGR. Service-fit factor 30% is an ASSUMPTION (destruction/disposal services only; excludes robots, PPE, training).
B12: 3. Humanitarian mine action funding, global | C12: 1070 | D12: 1 | E12: =C12*D12 | F12: 0.01 | G12: SOURCED: Landmine Monitor 2025 — $1.07bn in 2024. Growth held at 1% (funding fell in 2024; 2025 US cuts).
B13: 4. Sovereign end-of-life facility engineering (design-build of national demil / destruction plants) | C13: 500 | D13: 1 | E13: =C13*D13 | F13: 0.05 | G13: ASSUMPTION / PLACEHOLDER: a handful of national programmes per year at $50–150M each. No published aggregate.
B14: 5. Recovered materials from destroyed munitions (copper, brass, lead-antimony) sold into secondary markets | C14: 250 | D14: 1 | E14: =C14*D14 | F14: 0.03 | G14: ASSUMPTION: ~5% of the destruction-services layers at current metal prices (LME copper ~$14,000/t, lead ~$1,900/t, Sep 2026). Excludes DoD-owned material.
B15: TAM — allied munitions end-of-life, forming annual spend | E15: =SUM(E7:E14) | F15: =SUMPRODUCT(E7:E14,F7:F14)/E15
B16: Episodic layer — Ukraine explosive-hazard management need 2026–2035 (total, not annual) | C16: 27600 | G16: SOURCED: World Bank / Govt of Ukraine RDNA5, 23 Feb 2026 — supersedes RDNA4 $29.8bn.
B17: → average per year over ten years | E17: =C16/10
B19: SAM — North America + Europe; small-arms-through-artillery destruction, materials recovery, plant engineering (the scope the roadmap assembles)
B20: Geographic reach factor (share of TAM in NA + Europe) | D20: 0.6
B21: Access factor (excludes G2G-only and prime-only work not open to a platform of this size) | D21: 0.7
B22: SAM (2026) | E22: =E15*D20*D21
B24: SAM grown to Year 5 and Year 10 at the blended TAM growth rate
B25: SAM Year 5 (2031) | E25: =E22*(1+F15)^5
B26: SAM Year 10 (2036) | E26: =E22*(1+F15)^10
B28: SOM — the model's own revenue, read against SAM
B29: Model revenue Year 5 (2031) | E29: ='P&L & Capital'!I12
B30: Implied share of Year-5 SAM | E30: =IF(E25=0,0,E29/E25)
B31: Model revenue Year 10 (2036) | E31: ='P&L & Capital'!N12
B32: Implied share of Year-10 SAM | E32: =IF(E26=0,0,E31/E26)
B34: Discipline: the platform is never scored on tons per year. The original August package's $15bn TAM (which included chemical-weapons demil and a modelled $2.5bn ammunition-demil line with no source) has been replaced by this layered construction.

Sheet Organic Build
B2: Organic build — what the platform earns from what it operates and develops (USD M)
B3: Fleet-driven custody destruction services, equipment sales, allied/sovereign programmes, post-conflict programmes, metals recovery. All drivers on Inputs.
B6: USD millions unless noted | C6: Input / note | D6: 2026 | E6: 2027 | F6: 2028 | G6: 2029 | H6: 2030 | I6: 2031 | J6: 2032 | K6: 2033 | L6: 2034 | M6: 2035 | N6: 2036
B7: Model year | D7: Y0 | E7: Y1 | F7: Y2 | G7: Y3 | H7: Y4 | I7: Y5 | J7: Y6 | K7: Y7 | L7: Y8 | M7: Y9 | N7: Y10
B9: A. Custody destruction services — eMACS fleet
B10: Units added in year | C10: count | D10: =Inputs!D59 | E10: =Inputs!E59 | F10: =Inputs!F59 | G10: =Inputs!G59 | H10: =Inputs!H59 | I10: =Inputs!I59 | J10: =Inputs!J59 | K10: =Inputs!K59 | ... N10: =Inputs!N59
B11: Units in service (year end) | C11: count | D11: =D10 | E11: =D11+E10 | F11: =E11+F10 | G11: =F11+G10 | H11: =G11+H10 | I11: =H11+I10 | J11: =I11+J10 | K11: =J11+K10 | L11: =K11+L10 | ... N11: =M11+N10
B12: Effective unit-years (new units at first-year utilisation) | C12: unit-yrs | D12: =D11 | E12: =D11+E10*Inputs!$C$14 | F12: =E11+F10*Inputs!$C$14 | G12: =F11+G10*Inputs!$C$14 | H12: =G11+H10*Inputs!$C$14 | I12: =H11+I10*Inputs!$C$14 | J12: =I11+J10*Inputs!$C$14 | K12: =J11+K10*Inputs!$C$14 | L12: =K11+L10*Inputs!$C$14 | ... N12: =M11+N10*Inputs!$C$14
B13: Revenue per unit-year (escalated) | C13: USD M | D13: =Inputs!$C$12 | E13: =D13*(1+Inputs!$C$13) | F13: =E13*(1+Inputs!$C$13) | G13: =F13*(1+Inputs!$C$13) | H13: =G13*(1+Inputs!$C$13) | I13: =H13*(1+Inputs!$C$13) | J13: =I13*(1+Inputs!$C$13) | K13: =J13*(1+Inputs!$C$13) | L13: =K13*(1+Inputs!$C$13) | ... N13: =M13*(1+Inputs!$C$13)
B14: Custody destruction services revenue | D14: =Baseline!$D$31 | E14: =E12*E13 | F14: =F12*F13 | G14: =G12*G13 | H14: =H12*H13 | I14: =I12*I13 | J14: =J12*J13 | K14: =K12*K13 | L14: =L12*L13 | ... N14: =N12*N13
B15: Y0 (2026) = the Baseline FY2026 placeholder (defaults to the FY2025 actual). Fleet × rate applies from 2027, when the US entity and fleet additions come into service.
B17: B. Equipment sales via agents
B18: Units sold | C18: count | D18: =MAX(Baseline!$D$32,Inputs!D65) | E18: =Inputs!E65 | F18: =Inputs!F65 | G18: =Inputs!G65 | H18: =Inputs!H65 | I18: =Inputs!I65 | J18: =Inputs!J65 | K18: =Inputs!K65 | L18: =Inputs!L65 | ... N18: =Inputs!N65
B19: Equipment sales revenue | D19: =D18*Inputs!$C$16*(1+Inputs!$C$13)^0 | E19: =E18*Inputs!$C$16*(1+Inputs!$C$13)^1 | F19: =F18*Inputs!$C$16*(1+Inputs!$C$13)^2 | G19: =G18*Inputs!$C$16*(1+Inputs!$C$13)^3 | H19: =H18*Inputs!$C$16*(1+Inputs!$C$13)^4 | I19: =I18*Inputs!$C$16*(1+Inputs!$C$13)^5 | J19: =J18*Inputs!$C$16*(1+Inputs!$C$13)^6 | K19: =K18*Inputs!$C$16*(1+Inputs!$C$13)^7 | L19: =L18*Inputs!$C$16*(1+Inputs!$C$13)^8 | M19: =M18*Inputs!$C$16*(1+Inputs!$C$13)^9 | N19: =N18*Inputs!$C$16*(1+Inputs!$C$13)^10
B21: C. Allied / sovereign programmes (Phase 3 offer: design, build, operate, certify)
B22: Programmes active | C22: count | D22: =Inputs!D71 | E22: =Inputs!E71 | F22: =Inputs!F71 | G22: =Inputs!G71 | H22: =Inputs!H71 | I22: =Inputs!I71 | J22: =Inputs!J71 | K22: =Inputs!K71 | ... N22: =Inputs!N71
B23: Allied / sovereign programme revenue | D23: =D22*Inputs!$C$17*(1+Inputs!$C$13)^0 | E23: =E22*Inputs!$C$17*(1+Inputs!$C$13)^1 | F23: =F22*Inputs!$C$17*(1+Inputs!$C$13)^2 | G23: =G22*Inputs!$C$17*(1+Inputs!$C$13)^3 | H23: =H22*Inputs!$C$17*(1+Inputs!$C$13)^4 | I23: =I22*Inputs!$C$17*(1+Inputs!$C$13)^5 | J23: =J22*Inputs!$C$17*(1+Inputs!$C$13)^6 | K23: =K22*Inputs!$C$17*(1+Inputs!$C$13)^7 | L23: =L22*Inputs!$C$17*(1+Inputs!$C$13)^8 | M23: =M22*Inputs!$C$17*(1+Inputs!$C$13)^9 | N23: =N22*Inputs!$C$17*(1+Inputs!$C$13)^10
B25: D. Post-conflict / clearance programmes
B26: Programme-years | C26: count | D26: =Inputs!D77 | E26: =Inputs!E77 | F26: =Inputs!F77 | G26: =Inputs!G77 | H26: =Inputs!H77 | I26: =Inputs!I77 | J26: =Inputs!J77 | K26: =Inputs!K77 | ... N26: =Inputs!N77
B27: Post-conflict programme revenue | D27: =D26*Inputs!$C$18*(1+Inputs!$C$13)^0 | E27: =E26*Inputs!$C$18*(1+Inputs!$C$13)^1 | F27: =F26*Inputs!$C$18*(1+Inputs!$C$13)^2 | G27: =G26*Inputs!$C$18*(1+Inputs!$C$13)^3 | H27: =H26*Inputs!$C$18*(1+Inputs!$C$13)^4 | I27: =I26*Inputs!$C$18*(1+Inputs!$C$13)^5 | J27: =J26*Inputs!$C$18*(1+Inputs!$C$13)^6 | K27: =K26*Inputs!$C$18*(1+Inputs!$C$13)^7 | L27: =L26*Inputs!$C$18*(1+Inputs!$C$13)^8 | M27: =M26*Inputs!$C$18*(1+Inputs!$C$13)^9 | N27: =N26*Inputs!$C$18*(1+Inputs!$C$13)^10
B29: E. Metals recovery (on custody destruction services only)
B30: Metals recovery revenue | D30: =D14*Inputs!$C$15 | E30: =E14*Inputs!$C$15 | F30: =F14*Inputs!$C$15 | G30: =G14*Inputs!$C$15 | H30: =H14*Inputs!$C$15 | I30: =I14*Inputs!$C$15 | J30: =J14*Inputs!$C$15 | K30: =K14*Inputs!$C$15 | ... N30: =N14*Inputs!$C$15
B31: Not applied to acquired businesses (their own recovery economics sit inside their revenue) nor to US DoD demil services (Army sells the material, 10 USC 7690).
B33: F. Organic revenue and contribution
B34: Total organic revenue | D34: =D14+D19+D23+D27+D30 | E34: =E14+E19+E23+E27+E30 | F34: =F14+F19+F23+F27+F30 | G34: =G14+G19+G23+G27+G30 | H34: =H14+H19+H23+H27+H30 | I34: =I14+I19+I23+I27+I30 | J34: =J14+J19+J23+J27+J30 | K34: =K14+K19+K23+K27+K30 | ... N34: =N14+N19+N23+N27+N30
B35: Organic EBITDA contribution (before corporate cost) | D35: =D14*Inputs!$C$20+D19*Inputs!$C$21+D23*Inputs!$C$22+D27*Inputs!$C$23+D30*Inputs!$C$24 | E35: =E14*Inputs!$C$20+E19*Inputs!$C$21+E23*Inputs!$C$22+E27*Inputs!$C$23+E30*Inputs!$C$24 | F35: =F14*Inputs!$C$20+F19*Inputs!$C$21+F23*Inputs!$C$22+F27*Inputs!$C$23+F30*Inputs!$C$24 | G35: =G14*Inputs!$C$20+G19*Inputs!$C$21+G23*Inputs!$C$22+G27*Inputs!$C$23+G30*Inputs!$C$24 | H35: =H14*Inputs!$C$20+H19*Inputs!$C$21+H23*Inputs!$C$22+H27*Inputs!$C$23+H30*Inputs!$C$24 | I35: =I14*Inputs!$C$20+I19*Inputs!$C$21+I23*Inputs!$C$22+I27*Inputs!$C$23+I30*Inputs!$C$24 | J35: =J14*Inputs!$C$20+J19*Inputs!$C$21+J23*Inputs!$C$22+J27*Inputs!$C$23+J30*Inputs!$C$24 | K35: =K14*Inputs!$C$20+K19*Inputs!$C$21+K23*Inputs!$C$22+K27*Inputs!$C$23+K30*Inputs!$C$24 | ... N35: =N14*Inputs!$C$20+N19*Inputs!$C$21+N23*Inputs!$C$22+N27*Inputs!$C$23+N30*Inputs!$C$24
B36: Organic contribution margin | D36: =IF(D34=0,0,D35/D34) | E36: =IF(E34=0,0,E35/E34) | F36: =IF(F34=0,0,F35/F34) | G36: =IF(G34=0,0,G35/G34) | H36: =IF(H34=0,0,H35/H34) | I36: =IF(I34=0,0,I35/I34) | J36: =IF(J34=0,0,J35/J34) | K36: =IF(K34=0,0,K35/K34) | ... N36: =IF(N34=0,0,N35/N34)

Sheet Acquisitions
B2: Acquisition programme — capability acquisitions, deal by deal (USD M)
B3: Capability categories only; named targets are held for diligence. Entry revenue, margin and multiple are ASSUMPTIONS bounded by sourced transaction and lower-middle-market data (Sources tab).
B6: Capability category | C6: Base close yr | D6: Live close yr | E6: Entry rev | F6: EBITDA margin | G6: EV/EBITDA | H6: On (1/0) | I6: Price (live basis) | J6: Integration cost | K6: Price at rev. mult.
B7: Large-calibre & artillery demilitarization | C7: 2028 | D7: =C7+Inputs!$C$32 | E7: 18 | F7: 0.18 | G7: 5.5 | H7: =CHOOSE(Inputs!$C$6,1,1,1) | I7: =H7*IF(Inputs!$C$33=1,E7*F7*G7,E7*Inputs!$C$34) | J7: =I7*Inputs!$C$31 | K7: =H7*E7*Inputs!$C$34
B8: Metals recovery & reclamation | C8: 2028 | D8: =C8+Inputs!$C$32 | E8: 15 | F8: 0.12 | G8: 5 | H8: =CHOOSE(Inputs!$C$6,1,1,1) | I8: =H8*IF(Inputs!$C$33=1,E8*F8*G8,E8*Inputs!$C$34) | J8: =I8*Inputs!$C$31 | K8: =H8*E8*Inputs!$C$34
B9: Plant & equipment engineering | C9: 2029 | D9: =C9+Inputs!$C$32 | E9: 12 | F9: 0.15 | G9: 5.5 | H9: =CHOOSE(Inputs!$C$6,1,1,1) | I9: =H9*IF(Inputs!$C$33=1,E9*F9*G9,E9*Inputs!$C$34) | J9: =I9*Inputs!$C$31 | K9: =H9*E9*Inputs!$C$34
B10: Secure destruction — military & conflict customers | C10: 2030 | D10: =C10+Inputs!$C$32 | E10: 10 | F10: 0.2 | G10: 6 | H10: =CHOOSE(Inputs!$C$6,1,1,1) | I10: =H10*IF(Inputs!$C$33=1,E10*F10*G10,E10*Inputs!$C$34) | J10: =I10*Inputs!$C$31 | K10: =H10*E10*Inputs!$C$34
B11: European demilitarization operating business | C11: 2031 | D11: =C11+Inputs!$C$32 | E11: 20 | F11: 0.18 | G11: 6 | H11: =CHOOSE(Inputs!$C$6,0,1,1) | I11: =H11*IF(Inputs!$C$33=1,E11*F11*G11,E11*Inputs!$C$34) | J11: =I11*Inputs!$C$31 | K11: =H11*E11*Inputs!$C$34
B12: Energetics / second recovery capability | C12: 2033 | D12: =C12+Inputs!$C$32 | E12: 15 | F12: 0.15 | G12: 5.5 | H12: =CHOOSE(Inputs!$C$6,0,1,1) | I12: =H12*IF(Inputs!$C$33=1,E12*F12*G12,E12*Inputs!$C$34) | J12: =I12*Inputs!$C$31 | K12: =H12*E12*Inputs!$C$34
B13: Additional platform deal (Upside only) | C13: 2030 | D13: =C13+Inputs!$C$32 | E13: 20 | F13: 0.18 | G13: 6 | H13: =CHOOSE(Inputs!$C$6,0,0,1) | I13: =H13*IF(Inputs!$C$33=1,E13*F13*G13,E13*Inputs!$C$34) | J13: =I13*Inputs!$C$31 | K13: =H13*E13*Inputs!$C$34
B14: Total programme (live) | E14: =SUMPRODUCT(H7:H13,E7:E13) | I14: =SUM(I7:I13) | J14: =SUM(J7:J13) | K14: =SUM(K7:K13)
B15: Deals on (count) | H15: =SUM(H7:H13)
B16: Implied blended price / entry revenue | I16: =IF(E14=0,0,I14/E14)
B17: Reference: disclosed sector transactions 2023–26 cleared ~1.5–3.4x revenue (Cadre–Carr's 1.5x, Cadre–ICOR 2.3x, Cadre–Alpha Safety 2.4x, Rheinmetall–Expal 3.4x). Founder-held sub-$20M businesses trade at 4–7x EBITDA (GF Data / Pepperdine). Column K shows the revenue-multiple stress price.
B20: USD millions unless noted | C20: Input / note | D20: 2026 | E20: 2027 | F20: 2028 | G20: 2029 | H20: 2030 | I20: 2031 | J20: 2032 | K20: 2033 | L20: 2034 | M20: 2035 | N20: 2036
B21: Model year | D21: Y0 | E21: Y1 | F21: Y2 | G21: Y3 | H21: Y4 | I21: Y5 | J21: Y6 | K21: Y7 | L21: Y8 | M21: Y9 | N21: Y10
B23: Acquired revenue by deal (grows at post-acquisition rate from the year after close)
B24: Large-calibre & artillery demilitarization | D24: =IF(OR($H$7=0,D$20<$D$7),0,$E$7*(1+Inputs!$C$29)^(D$20-$D$7)) | E24: =IF(OR($H$7=0,E$20<$D$7),0,$E$7*(1+Inputs!$C$29)^(E$20-$D$7)) | F24: =IF(OR($H$7=0,F$20<$D$7),0,$E$7*(1+Inputs!$C$29)^(F$20-$D$7)) | G24: =IF(OR($H$7=0,G$20<$D$7),0,$E$7*(1+Inputs!$C$29)^(G$20-$D$7)) | H24: =IF(OR($H$7=0,H$20<$D$7),0,$E$7*(1+Inputs!$C$29)^(H$20-$D$7)) | I24: =IF(OR($H$7=0,I$20<$D$7),0,$E$7*(1+Inputs!$C$29)^(I$20-$D$7)) | J24: =IF(OR($H$7=0,J$20<$D$7),0,$E$7*(1+Inputs!$C$29)^(J$20-$D$7)) | K24: =IF(OR($H$7=0,K$20<$D$7),0,$E$7*(1+Inputs!$C$29)^(K$20-$D$7)) | ... N24: =IF(OR($H$7=0,N$20<$D$7),0,$E$7*(1+Inputs!$C$29)^(N$20-$D$7))
B25: Metals recovery & reclamation | D25: =IF(OR($H$8=0,D$20<$D$8),0,$E$8*(1+Inputs!$C$29)^(D$20-$D$8)) | E25: =IF(OR($H$8=0,E$20<$D$8),0,$E$8*(1+Inputs!$C$29)^(E$20-$D$8)) | F25: =IF(OR($H$8=0,F$20<$D$8),0,$E$8*(1+Inputs!$C$29)^(F$20-$D$8)) | G25: =IF(OR($H$8=0,G$20<$D$8),0,$E$8*(1+Inputs!$C$29)^(G$20-$D$8)) | H25: =IF(OR($H$8=0,H$20<$D$8),0,$E$8*(1+Inputs!$C$29)^(H$20-$D$8)) | I25: =IF(OR($H$8=0,I$20<$D$8),0,$E$8*(1+Inputs!$C$29)^(I$20-$D$8)) | J25: =IF(OR($H$8=0,J$20<$D$8),0,$E$8*(1+Inputs!$C$29)^(J$20-$D$8)) | K25: =IF(OR($H$8=0,K$20<$D$8),0,$E$8*(1+Inputs!$C$29)^(K$20-$D$8)) | ... N25: =IF(OR($H$8=0,N$20<$D$8),0,$E$8*(1+Inputs!$C$29)^(N$20-$D$8))
B26: Plant & equipment engineering | D26: =IF(OR($H$9=0,D$20<$D$9),0,$E$9*(1+Inputs!$C$29)^(D$20-$D$9)) | E26: =IF(OR($H$9=0,E$20<$D$9),0,$E$9*(1+Inputs!$C$29)^(E$20-$D$9)) | F26: =IF(OR($H$9=0,F$20<$D$9),0,$E$9*(1+Inputs!$C$29)^(F$20-$D$9)) | G26: =IF(OR($H$9=0,G$20<$D$9),0,$E$9*(1+Inputs!$C$29)^(G$20-$D$9)) | H26: =IF(OR($H$9=0,H$20<$D$9),0,$E$9*(1+Inputs!$C$29)^(H$20-$D$9)) | I26: =IF(OR($H$9=0,I$20<$D$9),0,$E$9*(1+Inputs!$C$29)^(I$20-$D$9)) | J26: =IF(OR($H$9=0,J$20<$D$9),0,$E$9*(1+Inputs!$C$29)^(J$20-$D$9)) | K26: =IF(OR($H$9=0,K$20<$D$9),0,$E$9*(1+Inputs!$C$29)^(K$20-$D$9)) | ... N26: =IF(OR($H$9=0,N$20<$D$9),0,$E$9*(1+Inputs!$C$29)^(N$20-$D$9))
B27: Secure destruction — military & conflict customers | D27: =IF(OR($H$10=0,D$20<$D$10),0,$E$10*(1+Inputs!$C$29)^(D$20-$D$10)) | E27: =IF(OR($H$10=0,E$20<$D$10),0,$E$10*(1+Inputs!$C$29)^(E$20-$D$10)) | F27: =IF(OR($H$10=0,F$20<$D$10),0,$E$10*(1+Inputs!$C$29)^(F$20-$D$10)) | G27: =IF(OR($H$10=0,G$20<$D$10),0,$E$10*(1+Inputs!$C$29)^(G$20-$D$10)) | H27: =IF(OR($H$10=0,H$20<$D$10),0,$E$10*(1+Inputs!$C$29)^(H$20-$D$10)) | I27: =IF(OR($H$10=0,I$20<$D$10),0,$E$10*(1+Inputs!$C$29)^(I$20-$D$10)) | J27: =IF(OR($H$10=0,J$20<$D$10),0,$E$10*(1+Inputs!$C$29)^(J$20-$D$10)) | K27: =IF(OR($H$10=0,K$20<$D$10),0,$E$10*(1+Inputs!$C$29)^(K$20-$D$10)) | ... N27: =IF(OR($H$10=0,N$20<$D$10),0,$E$10*(1+Inputs!$C$29)^(N$20-$D$10))
B28: European demilitarization operating business | D28: =IF(OR($H$11=0,D$20<$D$11),0,$E$11*(1+Inputs!$C$29)^(D$20-$D$11)) | E28: =IF(OR($H$11=0,E$20<$D$11),0,$E$11*(1+Inputs!$C$29)^(E$20-$D$11)) | F28: =IF(OR($H$11=0,F$20<$D$11),0,$E$11*(1+Inputs!$C$29)^(F$20-$D$11)) | G28: =IF(OR($H$11=0,G$20<$D$11),0,$E$11*(1+Inputs!$C$29)^(G$20-$D$11)) | H28: =IF(OR($H$11=0,H$20<$D$11),0,$E$11*(1+Inputs!$C$29)^(H$20-$D$11)) | I28: =IF(OR($H$11=0,I$20<$D$11),0,$E$11*(1+Inputs!$C$29)^(I$20-$D$11)) | J28: =IF(OR($H$11=0,J$20<$D$11),0,$E$11*(1+Inputs!$C$29)^(J$20-$D$11)) | K28: =IF(OR($H$11=0,K$20<$D$11),0,$E$11*(1+Inputs!$C$29)^(K$20-$D$11)) | ... N28: =IF(OR($H$11=0,N$20<$D$11),0,$E$11*(1+Inputs!$C$29)^(N$20-$D$11))
B29: Energetics / second recovery capability | D29: =IF(OR($H$12=0,D$20<$D$12),0,$E$12*(1+Inputs!$C$29)^(D$20-$D$12)) | E29: =IF(OR($H$12=0,E$20<$D$12),0,$E$12*(1+Inputs!$C$29)^(E$20-$D$12)) | F29: =IF(OR($H$12=0,F$20<$D$12),0,$E$12*(1+Inputs!$C$29)^(F$20-$D$12)) | G29: =IF(OR($H$12=0,G$20<$D$12),0,$E$12*(1+Inputs!$C$29)^(G$20-$D$12)) | H29: =IF(OR($H$12=0,H$20<$D$12),0,$E$12*(1+Inputs!$C$29)^(H$20-$D$12)) | I29: =IF(OR($H$12=0,I$20<$D$12),0,$E$12*(1+Inputs!$C$29)^(I$20-$D$12)) | J29: =IF(OR($H$12=0,J$20<$D$12),0,$E$12*(1+Inputs!$C$29)^(J$20-$D$12)) | K29: =IF(OR($H$12=0,K$20<$D$12),0,$E$12*(1+Inputs!$C$29)^(K$20-$D$12)) | ... N29: =IF(OR($H$12=0,N$20<$D$12),0,$E$12*(1+Inputs!$C$29)^(N$20-$D$12))
B30: Additional platform deal (Upside only) | D30: =IF(OR($H$13=0,D$20<$D$13),0,$E$13*(1+Inputs!$C$29)^(D$20-$D$13)) | E30: =IF(OR($H$13=0,E$20<$D$13),0,$E$13*(1+Inputs!$C$29)^(E$20-$D$13)) | F30: =IF(OR($H$13=0,F$20<$D$13),0,$E$13*(1+Inputs!$C$29)^(F$20-$D$13)) | G30: =IF(OR($H$13=0,G$20<$D$13),0,$E$13*(1+Inputs!$C$29)^(G$20-$D$13)) | H30: =IF(OR($H$13=0,H$20<$D$13),0,$E$13*(1+Inputs!$C$29)^(H$20-$D$13)) | I30: =IF(OR($H$13=0,I$20<$D$13),0,$E$13*(1+Inputs!$C$29)^(I$20-$D$13)) | J30: =IF(OR($H$13=0,J$20<$D$13),0,$E$13*(1+Inputs!$C$29)^(J$20-$D$13)) | K30: =IF(OR($H$13=0,K$20<$D$13),0,$E$13*(1+Inputs!$C$29)^(K$20-$D$13)) | ... N30: =IF(OR($H$13=0,N$20<$D$13),0,$E$13*(1+Inputs!$C$29)^(N$20-$D$13))
B31: Total acquired revenue | D31: =SUM(D24:D30) | E31: =SUM(E24:E30) | F31: =SUM(F24:F30) | G31: =SUM(G24:G30) | H31: =SUM(H24:H30) | I31: =SUM(I24:I30) | J31: =SUM(J24:J30) | K31: =SUM(K24:K30) | ... N31: =SUM(N24:N30)
B33: Acquired EBITDA by deal (entry margin, plus synergy uplift phased over three years)
B34: Large-calibre & artillery demilitarization | D34: =D24*($F$7+Inputs!$C$30*MIN(1,MAX(0,(D$20-$D$7))/3)) | E34: =E24*($F$7+Inputs!$C$30*MIN(1,MAX(0,(E$20-$D$7))/3)) | F34: =F24*($F$7+Inputs!$C$30*MIN(1,MAX(0,(F$20-$D$7))/3)) | G34: =G24*($F$7+Inputs!$C$30*MIN(1,MAX(0,(G$20-$D$7))/3)) | H34: =H24*($F$7+Inputs!$C$30*MIN(1,MAX(0,(H$20-$D$7))/3)) | I34: =I24*($F$7+Inputs!$C$30*MIN(1,MAX(0,(I$20-$D$7))/3)) | J34: =J24*($F$7+Inputs!$C$30*MIN(1,MAX(0,(J$20-$D$7))/3)) | K34: =K24*($F$7+Inputs!$C$30*MIN(1,MAX(0,(K$20-$D$7))/3)) | ... N34: =N24*($F$7+Inputs!$C$30*MIN(1,MAX(0,(N$20-$D$7))/3))
B35: Metals recovery & reclamation | D35: =D25*($F$8+Inputs!$C$30*MIN(1,MAX(0,(D$20-$D$8))/3)) | E35: =E25*($F$8+Inputs!$C$30*MIN(1,MAX(0,(E$20-$D$8))/3)) | F35: =F25*($F$8+Inputs!$C$30*MIN(1,MAX(0,(F$20-$D$8))/3)) | G35: =G25*($F$8+Inputs!$C$30*MIN(1,MAX(0,(G$20-$D$8))/3)) | H35: =H25*($F$8+Inputs!$C$30*MIN(1,MAX(0,(H$20-$D$8))/3)) | I35: =I25*($F$8+Inputs!$C$30*MIN(1,MAX(0,(I$20-$D$8))/3)) | J35: =J25*($F$8+Inputs!$C$30*MIN(1,MAX(0,(J$20-$D$8))/3)) | K35: =K25*($F$8+Inputs!$C$30*MIN(1,MAX(0,(K$20-$D$8))/3)) | ... N35: =N25*($F$8+Inputs!$C$30*MIN(1,MAX(0,(N$20-$D$8))/3))
B36: Plant & equipment engineering | D36: =D26*($F$9+Inputs!$C$30*MIN(1,MAX(0,(D$20-$D$9))/3)) | E36: =E26*($F$9+Inputs!$C$30*MIN(1,MAX(0,(E$20-$D$9))/3)) | F36: =F26*($F$9+Inputs!$C$30*MIN(1,MAX(0,(F$20-$D$9))/3)) | G36: =G26*($F$9+Inputs!$C$30*MIN(1,MAX(0,(G$20-$D$9))/3)) | H36: =H26*($F$9+Inputs!$C$30*MIN(1,MAX(0,(H$20-$D$9))/3)) | I36: =I26*($F$9+Inputs!$C$30*MIN(1,MAX(0,(I$20-$D$9))/3)) | J36: =J26*($F$9+Inputs!$C$30*MIN(1,MAX(0,(J$20-$D$9))/3)) | K36: =K26*($F$9+Inputs!$C$30*MIN(1,MAX(0,(K$20-$D$9))/3)) | ... N36: =N26*($F$9+Inputs!$C$30*MIN(1,MAX(0,(N$20-$D$9))/3))
B37: Secure destruction — military & conflict customers | D37: =D27*($F$10+Inputs!$C$30*MIN(1,MAX(0,(D$20-$D$10))/3)) | E37: =E27*($F$10+Inputs!$C$30*MIN(1,MAX(0,(E$20-$D$10))/3)) | F37: =F27*($F$10+Inputs!$C$30*MIN(1,MAX(0,(F$20-$D$10))/3)) | G37: =G27*($F$10+Inputs!$C$30*MIN(1,MAX(0,(G$20-$D$10))/3)) | H37: =H27*($F$10+Inputs!$C$30*MIN(1,MAX(0,(H$20-$D$10))/3)) | I37: =I27*($F$10+Inputs!$C$30*MIN(1,MAX(0,(I$20-$D$10))/3)) | J37: =J27*($F$10+Inputs!$C$30*MIN(1,MAX(0,(J$20-$D$10))/3)) | K37: =K27*($F$10+Inputs!$C$30*MIN(1,MAX(0,(K$20-$D$10))/3)) | ... N37: =N27*($F$10+Inputs!$C$30*MIN(1,MAX(0,(N$20-$D$10))/3))
B38: European demilitarization operating business | D38: =D28*($F$11+Inputs!$C$30*MIN(1,MAX(0,(D$20-$D$11))/3)) | E38: =E28*($F$11+Inputs!$C$30*MIN(1,MAX(0,(E$20-$D$11))/3)) | F38: =F28*($F$11+Inputs!$C$30*MIN(1,MAX(0,(F$20-$D$11))/3)) | G38: =G28*($F$11+Inputs!$C$30*MIN(1,MAX(0,(G$20-$D$11))/3)) | H38: =H28*($F$11+Inputs!$C$30*MIN(1,MAX(0,(H$20-$D$11))/3)) | I38: =I28*($F$11+Inputs!$C$30*MIN(1,MAX(0,(I$20-$D$11))/3)) | J38: =J28*($F$11+Inputs!$C$30*MIN(1,MAX(0,(J$20-$D$11))/3)) | K38: =K28*($F$11+Inputs!$C$30*MIN(1,MAX(0,(K$20-$D$11))/3)) | ... N38: =N28*($F$11+Inputs!$C$30*MIN(1,MAX(0,(N$20-$D$11))/3))
B39: Energetics / second recovery capability | D39: =D29*($F$12+Inputs!$C$30*MIN(1,MAX(0,(D$20-$D$12))/3)) | E39: =E29*($F$12+Inputs!$C$30*MIN(1,MAX(0,(E$20-$D$12))/3)) | F39: =F29*($F$12+Inputs!$C$30*MIN(1,MAX(0,(F$20-$D$12))/3)) | G39: =G29*($F$12+Inputs!$C$30*MIN(1,MAX(0,(G$20-$D$12))/3)) | H39: =H29*($F$12+Inputs!$C$30*MIN(1,MAX(0,(H$20-$D$12))/3)) | I39: =I29*($F$12+Inputs!$C$30*MIN(1,MAX(0,(I$20-$D$12))/3)) | J39: =J29*($F$12+Inputs!$C$30*MIN(1,MAX(0,(J$20-$D$12))/3)) | K39: =K29*($F$12+Inputs!$C$30*MIN(1,MAX(0,(K$20-$D$12))/3)) | ... N39: =N29*($F$12+Inputs!$C$30*MIN(1,MAX(0,(N$20-$D$12))/3))
B40: Additional platform deal (Upside only) | D40: =D30*($F$13+Inputs!$C$30*MIN(1,MAX(0,(D$20-$D$13))/3)) | E40: =E30*($F$13+Inputs!$C$30*MIN(1,MAX(0,(E$20-$D$13))/3)) | F40: =F30*($F$13+Inputs!$C$30*MIN(1,MAX(0,(F$20-$D$13))/3)) | G40: =G30*($F$13+Inputs!$C$30*MIN(1,MAX(0,(G$20-$D$13))/3)) | H40: =H30*($F$13+Inputs!$C$30*MIN(1,MAX(0,(H$20-$D$13))/3)) | I40: =I30*($F$13+Inputs!$C$30*MIN(1,MAX(0,(I$20-$D$13))/3)) | J40: =J30*($F$13+Inputs!$C$30*MIN(1,MAX(0,(J$20-$D$13))/3)) | K40: =K30*($F$13+Inputs!$C$30*MIN(1,MAX(0,(K$20-$D$13))/3)) | ... N40: =N30*($F$13+Inputs!$C$30*MIN(1,MAX(0,(N$20-$D$13))/3))
B41: Total acquired EBITDA | D41: =SUM(D34:D40) | E41: =SUM(E34:E40) | F41: =SUM(F34:F40) | G41: =SUM(G34:G40) | H41: =SUM(H34:H40) | I41: =SUM(I34:I40) | J41: =SUM(J34:J40) | K41: =SUM(K34:K40) | ... N41: =SUM(N34:N40)
B43: Cash spent on acquisitions
B44: Purchase consideration paid in year | D44: =SUMPRODUCT(($D$7:$D$13=D$20)*$I$7:$I$13) | E44: =SUMPRODUCT(($D$7:$D$13=E$20)*$I$7:$I$13) | F44: =SUMPRODUCT(($D$7:$D$13=F$20)*$I$7:$I$13) | G44: =SUMPRODUCT(($D$7:$D$13=G$20)*$I$7:$I$13) | H44: =SUMPRODUCT(($D$7:$D$13=H$20)*$I$7:$I$13) | I44: =SUMPRODUCT(($D$7:$D$13=I$20)*$I$7:$I$13) | J44: =SUMPRODUCT(($D$7:$D$13=J$20)*$I$7:$I$13) | K44: =SUMPRODUCT(($D$7:$D$13=K$20)*$I$7:$I$13) | ... N44: =SUMPRODUCT(($D$7:$D$13=N$20)*$I$7:$I$13)
B45: Integration cost in year | D45: =SUMPRODUCT(($D$7:$D$13=D$20)*$J$7:$J$13) | E45: =SUMPRODUCT(($D$7:$D$13=E$20)*$J$7:$J$13) | F45: =SUMPRODUCT(($D$7:$D$13=F$20)*$J$7:$J$13) | G45: =SUMPRODUCT(($D$7:$D$13=G$20)*$J$7:$J$13) | H45: =SUMPRODUCT(($D$7:$D$13=H$20)*$J$7:$J$13) | I45: =SUMPRODUCT(($D$7:$D$13=I$20)*$J$7:$J$13) | J45: =SUMPRODUCT(($D$7:$D$13=J$20)*$J$7:$J$13) | K45: =SUMPRODUCT(($D$7:$D$13=K$20)*$J$7:$J$13) | ... N45: =SUMPRODUCT(($D$7:$D$13=N$20)*$J$7:$J$13)
B46: Deals closing in year | D46: =SUMPRODUCT(($D$7:$D$13=D$20)*$H$7:$H$13) | E46: =SUMPRODUCT(($D$7:$D$13=E$20)*$H$7:$H$13) | F46: =SUMPRODUCT(($D$7:$D$13=F$20)*$H$7:$H$13) | G46: =SUMPRODUCT(($D$7:$D$13=G$20)*$H$7:$H$13) | H46: =SUMPRODUCT(($D$7:$D$13=H$20)*$H$7:$H$13) | I46: =SUMPRODUCT(($D$7:$D$13=I$20)*$H$7:$H$13) | J46: =SUMPRODUCT(($D$7:$D$13=J$20)*$H$7:$H$13) | K46: =SUMPRODUCT(($D$7:$D$13=K$20)*$H$7:$H$13) | ... N46: =SUMPRODUCT(($D$7:$D$13=N$20)*$H$7:$H$13)
B47: Cumulative deals closed | D47: =D46 | E47: =D47+E46 | F47: =E47+F46 | G47: =F47+G46 | H47: =G47+H46 | I47: =H47+I46 | J47: =I47+J46 | K47: =J47+K46 | L47: =K47+L46 | ... N47: =M47+N46
B48: Memo: consideration at revenue-multiple stress price | D48: =SUMPRODUCT(($D$7:$D$13=D$20)*$K$7:$K$13) | E48: =SUMPRODUCT(($D$7:$D$13=E$20)*$K$7:$K$13) | F48: =SUMPRODUCT(($D$7:$D$13=F$20)*$K$7:$K$13) | G48: =SUMPRODUCT(($D$7:$D$13=G$20)*$K$7:$K$13) | H48: =SUMPRODUCT(($D$7:$D$13=H$20)*$K$7:$K$13) | I48: =SUMPRODUCT(($D$7:$D$13=I$20)*$K$7:$K$13) | J48: =SUMPRODUCT(($D$7:$D$13=J$20)*$K$7:$K$13) | K48: =SUMPRODUCT(($D$7:$D$13=K$20)*$K$7:$K$13) | ... N48: =SUMPRODUCT(($D$7:$D$13=N$20)*$K$7:$K$13)

Sheet P&L & Capital
B2: Consolidated P&L, cash and capital requirement (USD M)
B3: Organic + acquired. Capital requirement assumes equity funding of the whole plan (no acquisition debt) — conservative for a returns case.
B6: USD millions unless noted | C6: Input / note | D6: 2026 | E6: 2027 | F6: 2028 | G6: 2029 | H6: 2030 | I6: 2031 | J6: 2032 | K6: 2033 | L6: 2034 | M6: 2035 | N6: 2036
B7: Model year | D7: Y0 | E7: Y1 | F7: Y2 | G7: Y3 | H7: Y4 | I7: Y5 | J7: Y6 | K7: Y7 | L7: Y8 | M7: Y9 | N7: Y10
B9: Revenue
B10: Organic revenue | D10: ='Organic Build'!D34 | E10: ='Organic Build'!E34 | F10: ='Organic Build'!F34 | G10: ='Organic Build'!G34 | H10: ='Organic Build'!H34 | I10: ='Organic Build'!I34 | J10: ='Organic Build'!J34 | K10: ='Organic Build'!K34 | ... N10: ='Organic Build'!N34
B11: Acquired revenue | D11: =Acquisitions!D31 | E11: =Acquisitions!E31 | F11: =Acquisitions!F31 | G11: =Acquisitions!G31 | H11: =Acquisitions!H31 | I11: =Acquisitions!I31 | J11: =Acquisitions!J31 | K11: =Acquisitions!K31 | ... N11: =Acquisitions!N31
B12: TOTAL REVENUE | D12: =D10+D11 | E12: =E10+E11 | F12: =F10+F11 | G12: =G10+G11 | H12: =H10+H11 | I12: =I10+I11 | J12: =J10+J11 | K12: =K10+K11 | ... N12: =N10+N11
B13: Growth y/y | E13: =IF(D12=0,0,E12/D12-1) | F13: =IF(E12=0,0,F12/E12-1) | G13: =IF(F12=0,0,G12/F12-1) | H13: =IF(G12=0,0,H12/G12-1) | I13: =IF(H12=0,0,I12/H12-1) | J13: =IF(I12=0,0,J12/I12-1) | K13: =IF(J12=0,0,K12/J12-1) | L13: =IF(K12=0,0,L12/K12-1) | ... N13: =IF(M12=0,0,N12/M12-1)
B14: Acquired share of revenue | D14: =IF(D12=0,0,D11/D12) | E14: =IF(E12=0,0,E11/E12) | F14: =IF(F12=0,0,F11/F12) | G14: =IF(G12=0,0,G11/G12) | H14: =IF(H12=0,0,H11/H12) | I14: =IF(I12=0,0,I11/I12) | J14: =IF(J12=0,0,J11/J12) | K14: =IF(K12=0,0,K11/K12) | ... N14: =IF(N12=0,0,N11/N12)
B16: EBITDA
B17: Organic contribution | D17: ='Organic Build'!D35 | E17: ='Organic Build'!E35 | F17: ='Organic Build'!F35 | G17: ='Organic Build'!G35 | H17: ='Organic Build'!H35 | I17: ='Organic Build'!I35 | J17: ='Organic Build'!J35 | K17: ='Organic Build'!K35 | ... N17: ='Organic Build'!N35
B18: Acquired EBITDA | D18: =Acquisitions!D41 | E18: =Acquisitions!E41 | F18: =Acquisitions!F41 | G18: =Acquisitions!G41 | H18: =Acquisitions!H41 | I18: =Acquisitions!I41 | J18: =Acquisitions!J41 | K18: =Acquisitions!K41 | ... N18: =Acquisitions!N41
B19: Corporate platform cost (Y0: bottom-up build) / margin-case override adjustment (Y1–Y10, sized to Inputs I93 target margin) | D19: =-(Inputs!D83*Inputs!$C$26+D11*Inputs!$C$27) | E19: =Inputs!E95*E12-E17-E18-E20 | F19: =Inputs!F95*F12-F17-F18-F20 | G19: =Inputs!G95*G12-G17-G18-G20 | H19: =Inputs!H95*H12-H17-H18-H20 | I19: =Inputs!I95*I12-I17-I18-I20 | J19: =Inputs!J95*J12-J17-J18-J20 | K19: =Inputs!K95*K12-K17-K18-K20 | L19: =Inputs!L95*L12-L17-L18-L20 | ... N19: =Inputs!N95*N12-N17-N18-N20
B20: Development & partnership programmes (expensed) | D20: =-Inputs!D89*Inputs!$C$39 | E20: =-Inputs!E89*Inputs!$C$39 | F20: =-Inputs!F89*Inputs!$C$39 | G20: =-Inputs!G89*Inputs!$C$39 | H20: =-Inputs!H89*Inputs!$C$39 | I20: =-Inputs!I89*Inputs!$C$39 | J20: =-Inputs!J89*Inputs!$C$39 | K20: =-Inputs!K89*Inputs!$C$39 | ... N20: =-Inputs!N89*Inputs!$C$39
B21: Integration costs (one-off) | D21: =-Acquisitions!D45 | E21: =-Acquisitions!E45 | F21: =-Acquisitions!F45 | G21: =-Acquisitions!G45 | H21: =-Acquisitions!H45 | I21: =-Acquisitions!I45 | J21: =-Acquisitions!J45 | K21: =-Acquisitions!K45 | ... N21: =-Acquisitions!N45
B22: EBITDA (reported, after one-offs) | D22: =SUM(D17:D21) | E22: =SUM(E17:E21) | F22: =SUM(F17:F21) | G22: =SUM(G17:G21) | H22: =SUM(H17:H21) | I22: =SUM(I17:I21) | J22: =SUM(J17:J21) | K22: =SUM(K17:K21) | ... N22: =SUM(N17:N21)
B23: Adjusted EBITDA (before integration one-offs) | D23: =D22-D21 | E23: =E22-E21 | F23: =F22-F21 | G23: =G22-G21 | H23: =H22-H21 | I23: =I22-I21 | J23: =J22-J21 | K23: =K22-K21 | ... N23: =N22-N21
B24: Adjusted EBITDA margin | D24: =IF(D12=0,0,D23/D12) | E24: =IF(E12=0,0,E23/E12) | F24: =IF(F12=0,0,F23/F12) | G24: =IF(G12=0,0,G23/G12) | H24: =IF(H12=0,0,H23/H12) | I24: =IF(I12=0,0,I23/I12) | J24: =IF(J12=0,0,J23/J12) | K24: =IF(K12=0,0,K23/K12) | ... N24: =IF(N12=0,0,N23/N12)
B26: Cash flow and capital requirement
B27: Cash taxes (on positive EBITDA less D&A; simplified) | D27: =-MAX(0,D22-D12*Inputs!$C$41)*Inputs!$C$40 | E27: =-MAX(0,E22-E12*Inputs!$C$41)*Inputs!$C$40 | F27: =-MAX(0,F22-F12*Inputs!$C$41)*Inputs!$C$40 | G27: =-MAX(0,G22-G12*Inputs!$C$41)*Inputs!$C$40 | H27: =-MAX(0,H22-H12*Inputs!$C$41)*Inputs!$C$40 | I27: =-MAX(0,I22-I12*Inputs!$C$41)*Inputs!$C$40 | J27: =-MAX(0,J22-J12*Inputs!$C$41)*Inputs!$C$40 | K27: =-MAX(0,K22-K12*Inputs!$C$41)*Inputs!$C$40 | ... N27: =-MAX(0,N22-N12*Inputs!$C$41)*Inputs!$C$40
B28: Fleet capex (units built for own operation) | D28: =0 | E28: =-'Organic Build'!E10*Inputs!$C$36 | F28: =-'Organic Build'!F10*Inputs!$C$36 | G28: =-'Organic Build'!G10*Inputs!$C$36 | H28: =-'Organic Build'!H10*Inputs!$C$36 | I28: =-'Organic Build'!I10*Inputs!$C$36 | J28: =-'Organic Build'!J10*Inputs!$C$36 | K28: =-'Organic Build'!K10*Inputs!$C$36 | L28: =-'Organic Build'!L10*Inputs!$C$36 | ... N28: =-'Organic Build'!N10*Inputs!$C$36
B29: Maintenance capex | D29: =-D12*Inputs!$C$37 | E29: =-E12*Inputs!$C$37 | F29: =-F12*Inputs!$C$37 | G29: =-G12*Inputs!$C$37 | H29: =-H12*Inputs!$C$37 | I29: =-I12*Inputs!$C$37 | J29: =-J12*Inputs!$C$37 | K29: =-K12*Inputs!$C$37 | ... N29: =-N12*Inputs!$C$37
B30: Working capital investment | D30: =0 | E30: =-MAX(0,E12-D12)*Inputs!$C$38 | F30: =-MAX(0,F12-E12)*Inputs!$C$38 | G30: =-MAX(0,G12-F12)*Inputs!$C$38 | H30: =-MAX(0,H12-G12)*Inputs!$C$38 | I30: =-MAX(0,I12-H12)*Inputs!$C$38 | J30: =-MAX(0,J12-I12)*Inputs!$C$38 | K30: =-MAX(0,K12-J12)*Inputs!$C$38 | L30: =-MAX(0,L12-K12)*Inputs!$C$38 | ... N30: =-MAX(0,N12-M12)*Inputs!$C$38
B31: Acquisition consideration | D31: =-Acquisitions!D44 | E31: =-Acquisitions!E44 | F31: =-Acquisitions!F44 | G31: =-Acquisitions!G44 | H31: =-Acquisitions!H44 | I31: =-Acquisitions!I44 | J31: =-Acquisitions!J44 | K31: =-Acquisitions!K44 | ... N31: =-Acquisitions!N44
B32: Net cash flow before financing | D32: =D22+SUM(D27:D31) | E32: =E22+SUM(E27:E31) | F32: =F22+SUM(F27:F31) | G32: =G22+SUM(G27:G31) | H32: =H22+SUM(H27:H31) | I32: =I22+SUM(I27:I31) | J32: =J22+SUM(J27:J31) | K32: =K22+SUM(K27:K31) | ... N32: =N22+SUM(N27:N31)
B33: Cumulative cash flow before financing (from opening cash) | D33: =Baseline!$D$33+D32 | E33: =D33+E32 | F33: =E33+F32 | G33: =F33+G32 | H33: =G33+H32 | I33: =H33+I32 | J33: =I33+J32 | K33: =J33+K32 | L33: =K33+L32 | ... N33: =M33+N32
B34: Equity funding drawn in year (to keep cash ≥ 0) | D34: =MAX(0,-D33) | E34: =MAX(0,-(D36+E32)) | F34: =MAX(0,-(E36+F32)) | G34: =MAX(0,-(F36+G32)) | H34: =MAX(0,-(G36+H32)) | I34: =MAX(0,-(H36+I32)) | J34: =MAX(0,-(I36+J32)) | K34: =MAX(0,-(J36+K32)) | L34: =MAX(0,-(K36+L32)) | ... N34: =MAX(0,-(M36+N32))
B35: Cumulative equity funding drawn | D35: =D34 | E35: =D35+E34 | F35: =E35+F34 | G35: =F35+G34 | H35: =G35+H34 | I35: =H35+I34 | J35: =I35+J34 | K35: =J35+K34 | L35: =K35+L34 | ... N35: =M35+N34
B36: Closing cash | D36: =Baseline!$D$33+D32+D34 | E36: =D36+E32+E34 | F36: =E36+F32+F34 | G36: =F36+G32+G34 | H36: =G36+H32+H34 | I36: =H36+I32+I34 | J36: =I36+J32+J34 | K36: =J36+K32+K34 | L36: =K36+L32+L34 | ... N36: =M36+N32+N34
B38: Capital required by phase (equity funding drawn) — the use-of-proceeds logic
B39: Phase | C39: Years | D39: USD M | F39: What it funds
B40: Phase 1 — Operate the foothold | C40: 2026–2027 | D40: =SUM(D34:E34) | F40: Fleet build-out, first allied programmes, development of the certification layer, platform team; first acquisitions negotiated.
B41: Phase 2 — Assemble the core | C41: 2028–2029 | D41: =SUM(F34:G34) | F41: First capability acquisitions (large-calibre demil, metals recovery, plant engineering), integration, partnerships.
B42: Phase 3 — The sovereign full-service offer | C42: 2030–2031 | D42: =SUM(H34:I34) | F42: Secure-destruction and European acquisitions; sovereign programme mobilisation; working capital.
B43: Later years | C43: 2032–2036 | D43: =SUM(J34:N34) | F43: Remaining acquisitions and growth — increasingly self-funded from platform cash flow.
B44: Total equity funding drawn, 2026–2036 | D44: =SUM(D40:D43)
B45: Of which acquisition consideration + integration | D45: =-SUM(D31:N31)-SUM(D21:N21)
B46: Memo: acquisition consideration if every deal priced at the revenue-multiple stress case | D46: =SUM(Acquisitions!D48:N48)
B47: Peak cumulative funding requirement | D47: =MAX(D35:N35)

Sheet Headcount
B2: Implied headcount (FTE)
B3: Revenue-per-FTE planning benchmarks — ASSUMPTIONS; acquired businesses bring their own staff at lower revenue/FTE.
B6: USD millions unless noted | C6: Input / note | D6: 2026 | E6: 2027 | F6: 2028 | G6: 2029 | H6: 2030 | I6: 2031 | J6: 2032 | K6: 2033 | L6: 2034 | M6: 2035 | N6: 2036
B7: Model year | D7: Y0 | E7: Y1 | F7: Y2 | G7: Y3 | H7: Y4 | I7: Y5 | J7: Y6 | K7: Y7 | L7: Y8 | M7: Y9 | N7: Y10
B9: Organic revenue per FTE (USD k) — field-operations-heavy services | C9: 200
B10: Acquired-business revenue per FTE (USD k) | C10: 160
B11: Corporate cost per corporate FTE (USD k, fully loaded) | C11: 180
B13: Organic operations FTE | D13: =MAX(4,'P&L & Capital'!D10*1000/$C$9) | E13: =MAX(4,'P&L & Capital'!E10*1000/$C$9) | F13: =MAX(4,'P&L & Capital'!F10*1000/$C$9) | G13: =MAX(4,'P&L & Capital'!G10*1000/$C$9) | H13: =MAX(4,'P&L & Capital'!H10*1000/$C$9) | I13: =MAX(4,'P&L & Capital'!I10*1000/$C$9) | J13: =MAX(4,'P&L & Capital'!J10*1000/$C$9) | K13: =MAX(4,'P&L & Capital'!K10*1000/$C$9) | ... N13: =MAX(4,'P&L & Capital'!N10*1000/$C$9)
B14: Acquired-business FTE | D14: ='P&L & Capital'!D11*1000/$C$10 | E14: ='P&L & Capital'!E11*1000/$C$10 | F14: ='P&L & Capital'!F11*1000/$C$10 | G14: ='P&L & Capital'!G11*1000/$C$10 | H14: ='P&L & Capital'!H11*1000/$C$10 | I14: ='P&L & Capital'!I11*1000/$C$10 | J14: ='P&L & Capital'!J11*1000/$C$10 | K14: ='P&L & Capital'!K11*1000/$C$10 | ... N14: ='P&L & Capital'!N11*1000/$C$10
B15: Corporate / platform FTE | D15: =-'P&L & Capital'!D19*1000/$C$11 | E15: =(Inputs!E83*Inputs!$C$26+'P&L & Capital'!E11*Inputs!$C$27)*1000/$C$11 | F15: =(Inputs!F83*Inputs!$C$26+'P&L & Capital'!F11*Inputs!$C$27)*1000/$C$11 | G15: =(Inputs!G83*Inputs!$C$26+'P&L & Capital'!G11*Inputs!$C$27)*1000/$C$11 | H15: =(Inputs!H83*Inputs!$C$26+'P&L & Capital'!H11*Inputs!$C$27)*1000/$C$11 | I15: =(Inputs!I83*Inputs!$C$26+'P&L & Capital'!I11*Inputs!$C$27)*1000/$C$11 | J15: =(Inputs!J83*Inputs!$C$26+'P&L & Capital'!J11*Inputs!$C$27)*1000/$C$11 | K15: =(Inputs!K83*Inputs!$C$26+'P&L & Capital'!K11*Inputs!$C$27)*1000/$C$11 | L15: =(Inputs!L83*Inputs!$C$26+'P&L & Capital'!L11*Inputs!$C$27)*1000/$C$11 | ... N15: =(Inputs!N83*Inputs!$C$26+'P&L & Capital'!N11*Inputs!$C$27)*1000/$C$11
B16: Total FTE | D16: =SUM(D13:D15) | E16: =SUM(E13:E15) | F16: =SUM(F13:F15) | G16: =SUM(G13:G15) | H16: =SUM(H13:H15) | I16: =SUM(I13:I15) | J16: =SUM(J13:J15) | K16: =SUM(K13:K15) | ... N16: =SUM(N13:N15)
B17: Blended revenue per FTE (USD k) | D17: =IF(D16=0,0,'P&L & Capital'!D12*1000/D16) | E17: =IF(E16=0,0,'P&L & Capital'!E12*1000/E16) | F17: =IF(F16=0,0,'P&L & Capital'!F12*1000/F16) | G17: =IF(G16=0,0,'P&L & Capital'!G12*1000/G16) | H17: =IF(H16=0,0,'P&L & Capital'!H12*1000/H16) | I17: =IF(I16=0,0,'P&L & Capital'!I12*1000/I16) | J17: =IF(J16=0,0,'P&L & Capital'!J12*1000/J16) | K17: =IF(K16=0,0,'P&L & Capital'!K12*1000/K16) | ... N17: =IF(N16=0,0,'P&L & Capital'!N12*1000/N16)

Sheet Returns & Valuation
B2: Returns case and Year-10 discounted-future-value bridge (USD M)
B3: Two lenses: (1) a private-equity returns case — exit at Year 5 or Year 7 at an EV/EBITDA multiple, against equity funded; (2) the corrected Year-10 DFV bridge from the August package.
B6: USD millions unless noted | C6: Input / note | D6: 2026 | E6: 2027 | F6: 2028 | G6: 2029 | H6: 2030 | I6: 2031 | J6: 2032 | K6: 2033 | L6: 2034 | M6: 2035 | N6: 2036
B7: Model year | D7: Y0 | E7: Y1 | F7: Y2 | G7: Y3 | H7: Y4 | I7: Y5 | J7: Y6 | K7: Y7 | L7: Y8 | M7: Y9 | N7: Y10
B9: 1. Returns case — equity funded per P&L & Capital, exit EV = adjusted EBITDA × exit multiple
B10: Equity invested in year (negative) | D10: =-'P&L & Capital'!D34 | E10: =-'P&L & Capital'!E34 | F10: =-'P&L & Capital'!F34 | G10: =-'P&L & Capital'!G34 | H10: =-'P&L & Capital'!H34 | I10: =-'P&L & Capital'!I34 | J10: =-'P&L & Capital'!J34 | K10: =-'P&L & Capital'!K34 | ... N10: =-'P&L & Capital'!N34
B11: Enterprise value if exited in year (adj. EBITDA × exit multiple) | D11: ='P&L & Capital'!D23*Inputs!$C$43 | E11: ='P&L & Capital'!E23*Inputs!$C$43 | F11: ='P&L & Capital'!F23*Inputs!$C$43 | G11: ='P&L & Capital'!G23*Inputs!$C$43 | H11: ='P&L & Capital'!H23*Inputs!$C$43 | I11: ='P&L & Capital'!I23*Inputs!$C$43 | J11: ='P&L & Capital'!J23*Inputs!$C$43 | K11: ='P&L & Capital'!K23*Inputs!$C$43 | ... N11: ='P&L & Capital'!N23*Inputs!$C$43
B12: Equity value at exit (EV + closing cash; no debt assumed) | D12: =D11+'P&L & Capital'!D36 | E12: =E11+'P&L & Capital'!E36 | F12: =F11+'P&L & Capital'!F36 | G12: =G11+'P&L & Capital'!G36 | H12: =H11+'P&L & Capital'!H36 | I12: =I11+'P&L & Capital'!I36 | J12: =J11+'P&L & Capital'!J36 | K12: =K11+'P&L & Capital'!K36 | ... N12: =N11+'P&L & Capital'!N36
B13: Cumulative equity invested to date | D13: ='P&L & Capital'!D35 | E13: ='P&L & Capital'!E35 | F13: ='P&L & Capital'!F35 | G13: ='P&L & Capital'!G35 | H13: ='P&L & Capital'!H35 | I13: ='P&L & Capital'!I35 | J13: ='P&L & Capital'!J35 | K13: ='P&L & Capital'!K35 | ... N13: ='P&L & Capital'!N35
B14: MOIC if exited in year | D14: =IF(D13=0,0,D12/D13) | E14: =IF(E13=0,0,E12/E13) | F14: =IF(F13=0,0,F12/F13) | G14: =IF(G13=0,0,G12/G13) | H14: =IF(H13=0,0,H12/H13) | I14: =IF(I13=0,0,I12/I13) | J14: =IF(J13=0,0,J12/J13) | K14: =IF(K13=0,0,K12/K13) | ... N14: =IF(N13=0,0,N12/N13)
B16: IRR series (investments to exit year, exit proceeds in exit year)
B17: Exit Year 5 (2031) — cash flows | D17: =D10 | E17: =E10 | F17: =F10 | G17: =G10 | H17: =H10 | I17: =I10+I12
B18: Exit Year 5 (2031) — IRR | C18: =IFERROR(IRR(D17:I17),0)
B19: Exit Year 5 (2031) — MOIC | C19: =I14
B21: Exit Year 7 (2033) — cash flows | D21: =D10 | E21: =E10 | F21: =F10 | G21: =G10 | H21: =H10 | I21: =I10 | J21: =J10 | K21: =K10+K12
B22: Exit Year 7 (2033) — IRR | C22: =IFERROR(IRR(D21:K21),0)
B23: Exit Year 7 (2033) — MOIC | C23: =K14
B25: Exit Year 10 (2036) — cash flows | D25: =D10 | E25: =E10 | F25: =F10 | G25: =G10 | H25: =H10 | I25: =I10 | J25: =J10 | K25: =K10 | ... M25: =M10 | N25: =N10+N12
B26: Exit Year 10 (2036) — IRR | C26: =IFERROR(IRR(D25:N25),0)
B27: Exit Year 10 (2036) — MOIC | C27: =N14
B29: Exit-multiple sensitivity — MOIC at Year 7
B30: Exit multiple | D30: 6 | E30: 8 | F30: 10 | G30: 12 | H30: 14
B31: MOIC (Year 7 exit) | D31: =IF(K13=0,0,('P&L & Capital'!K23*D30+'P&L & Capital'!K36)/K13) | E31: =IF(K13=0,0,('P&L & Capital'!K23*E30+'P&L & Capital'!K36)/K13) | F31: =IF(K13=0,0,('P&L & Capital'!K23*F30+'P&L & Capital'!K36)/K13) | G31: =IF(K13=0,0,('P&L & Capital'!K23*G30+'P&L & Capital'!K36)/K13) | H31: =IF(K13=0,0,('P&L & Capital'!K23*H30+'P&L & Capital'!K36)/K13)
B33: 2. Year-10 discounted-future-value bridge (corrected from the August 2026 package)
B34: Year-10 revenue (operating model) | C34: ='P&L & Capital'!N12
B35: Year-10 adjusted EBITDA margin (operating model — not a hard-coded 20%) | C35: ='P&L & Capital'!N24
B36: Year-10 adjusted EBITDA | C36: ='P&L & Capital'!N23
B37: Comp multiple — low (public A&D government services, KPMG end-2025) | C37: =Inputs!$C$45
B38: Comp multiple — high (Cadre Holdings trading, Aug 2026) | C38: =Inputs!$C$46
B39: Reference only: private A&D deal median 18.96x (PCE Q2 2026) — not used | C39: 18.96
B40: Future firm value — low | C40: =C36*C37
B41: Future firm value — high | C41: =C36*C38
B42: Discount rate | C42: =Inputs!$C$44
B43: Periods (matched to the 10-year projection horizon) | C43: 10
B44: Discounted firm value — low | C44: =C40/(1+C42)^C43
B45: Discounted firm value — high | C45: =C41/(1+C42)^C43
B46: Discounted firm value — midpoint | C46: =AVERAGE(C44:C45)
B47: Less: total equity funding drawn over the plan | C47: =-'P&L & Capital'!D44
B48: Discounted value net of capital deployed (midpoint) | C48: =C46+C47
B50: Sensitivity — discounted midpoint by discount rate × periods
B51: Discount rate \ periods | D51: 5 | E51: 7 | F51: 10
C52: 0.2 | D52: =AVERAGE(C40,C41)/(1+$C52)^D$51 | E52: =AVERAGE(C40,C41)/(1+$C52)^E$51 | F52: =AVERAGE(C40,C41)/(1+$C52)^F$51
C53: 0.25 | D53: =AVERAGE(C40,C41)/(1+$C53)^D$51 | E53: =AVERAGE(C40,C41)/(1+$C53)^E$51 | F53: =AVERAGE(C40,C41)/(1+$C53)^F$51
C54: 0.3 | D54: =AVERAGE(C40,C41)/(1+$C54)^D$51 | E54: =AVERAGE(C40,C41)/(1+$C54)^E$51 | F54: =AVERAGE(C40,C41)/(1+$C54)^F$51
C55: 0.35 | D55: =AVERAGE(C40,C41)/(1+$C55)^D$51 | E55: =AVERAGE(C40,C41)/(1+$C55)^E$51 | F55: =AVERAGE(C40,C41)/(1+$C55)^F$51
B56: Read: discounting fewer periods than the years projected inflates the headline; the bridge above uses 10 periods at the live discount rate. Comp multiples are trading/transaction data for far larger, de-risked businesses — a size and illiquidity discount is embedded in the discount rate, not in the multiple.

Sheet Scenarios
B2: Scenarios — lever settings and outcomes
B3: The "Live" column follows Inputs!C6. The three snapshot columns were captured at build time by running each case; re-run by changing the selector.
B5: Snapshot columns D–F are VALUES captured at build (1 Sep 2026) by running each scenario; column C is live.
B6: Metric | C6: Live | D6: Downside | E6: Base | F6: Upside
B7: Revenue Y5 (USD M) | C7: =Outputs!$C$11 | D7: 62.9101 | E7: 136.87071 | F7: 227.62251
B8: Revenue Y10 (USD M) | C8: =Outputs!$C$15 | D8: 115.27516 | E8: 341.63295 | F8: 693.79091
B9: Adj. EBITDA Y5 | C9: =Outputs!$C$19 | D9: 15.727525 | E9: 41.061214 | F9: 79.667879
B10: Adj. EBITDA Y10 | C10: =Outputs!$C$21 | D10: 34.582549 | E10: 119.57153 | F10: 277.51637
B11: Adj. EBITDA margin Y10 | C11: =Outputs!$C$23 | D11: 0.3 | E11: 0.35 | F11: 0.4
B12: Acquisitions (count) | C12: =Outputs!$C$24 | D12: 4 | E12: 6 | F12: 7
B13: Acquisition consideration (USD M) | C13: =Outputs!$C$25 | D13: 48.72 | E13: 82.695 | F13: 104.295
B14: Capital required Phases 1–3 (USD M) | C14: =Outputs!$C$29+Outputs!$C$30+Outputs!$C$31 | D14: 47.862518 | E14: 49.286891 | F14: 50.497047
B15: Total equity funding 2026–36 (USD M) | C15: =Outputs!$C$33 | D15: 47.862518 | E15: 49.286891 | F15: 50.497047
B16: Total FTE Y10 | C16: =Outputs!$C$51 | D16: 735.57689 | E16: 2020.1204 | F16: 3966.1521
B17: Share of SAM Y10 | C17: =Outputs!$C$59 | D17: 0.039260764 | E17: 0.11635438 | F17: 0.23629341
B18: MOIC — Year-7 exit | C18: =Outputs!$C$63 | D18: 4.1969439 | E18: 15.049575 | F18: 37.559014
B19: IRR — Year-7 exit | C19: =Outputs!$C$64 | D19: 0.45227943 | E19: 0.75521591 | F19: 1.1215058
B20: DFV midpoint (USD M) | C20: =Outputs!$C$73 | D20: 33.238343 | E20: 170.11537 | F20: 593.87086
B22: Lever settings by scenario
B23: Lever | D23: Downside | E23: Base | F23: Upside
B24: Revenue per deployed eMACS unit-year (USD M) | D24: =Inputs!D12 | E24: =Inputs!E12 | F24: =Inputs!F12
B25: Service price escalation per year | D25: =Inputs!D13 | E25: =Inputs!E13 | F25: =Inputs!F13
B26: First-year utilisation of a newly deployed unit | D26: =Inputs!D14 | E26: =Inputs!E14 | F26: =Inputs!F14
B27: Metals recovery contribution — % of custody destruction services revenue | D27: =Inputs!D15 | E27: =Inputs!E15 | F27: =Inputs!F15
B28: eMACS equipment sale price per unit (USD M) | D28: =Inputs!D16 | E28: =Inputs!E16 | F28: =Inputs!F16
B29: Average annual revenue per allied / sovereign programme (USD M) | D29: =Inputs!D17 | E29: =Inputs!E17 | F29: =Inputs!F17
B30: Post-conflict / clearance programme revenue at maturity (USD M per programme-year) | D30: =Inputs!D18 | E30: =Inputs!E18 | F30: =Inputs!F18
B31: Custody destruction services | D31: =Inputs!D20 | E31: =Inputs!E20 | F31: =Inputs!F20
B32: Equipment sales | D32: =Inputs!D21 | E32: =Inputs!E21 | F32: =Inputs!F21
B33: Allied / sovereign programmes | D33: =Inputs!D22 | E33: =Inputs!E22 | F33: =Inputs!F22
B34: Post-conflict programmes | D34: =Inputs!D23 | E34: =Inputs!E23 | F34: =Inputs!F23
B35: Metals recovery (contribution after processing & logistics) | D35: =Inputs!D24 | E35: =Inputs!E24 | F35: =Inputs!F24
B36: Corporate cost scale factor vs Base schedule | D36: =Inputs!D26 | E36: =Inputs!E26 | F36: =Inputs!F26
B37: Incremental platform overhead as % of acquired revenue | D37: =Inputs!D27 | E37: =Inputs!E27 | F37: =Inputs!F27
B38: Post-acquisition revenue growth of acquired businesses | D38: =Inputs!D29 | E38: =Inputs!E29 | F38: =Inputs!F29
B39: EBITDA margin uplift on acquired businesses by third year post-close (pts) | D39: =Inputs!D30 | E39: =Inputs!E30 | F39: =Inputs!F30
B40: One-off integration cost as % of purchase price | D40: =Inputs!D31 | E40: =Inputs!E31 | F40: =Inputs!F31
B41: Close-year shift applied to every deal (years; +1 = later) | D41: =Inputs!D32 | E41: =Inputs!E32 | F41: =Inputs!F32
B42: Fleet capex — cost to build one eMACS unit (USD M) | D42: =Inputs!D36 | E42: =Inputs!E36 | F42: =Inputs!F36
B43: Maintenance capex — % of total revenue | D43: =Inputs!D37 | E43: =Inputs!E37 | F43: =Inputs!F37
B44: Working capital — % of incremental revenue | D44: =Inputs!D38 | E44: =Inputs!E38 | F44: =Inputs!F38
B45: Development & partnership programme spend scale vs Base schedule | D45: =Inputs!D39 | E45: =Inputs!E39 | F45: =Inputs!F39
B46: Cash tax rate on positive EBIT (simplified) | D46: =Inputs!D40 | E46: =Inputs!E40 | F46: =Inputs!F40
B47: Depreciation & amortisation — % of revenue (for tax only) | D47: =Inputs!D41 | E47: =Inputs!E41 | F47: =Inputs!F41
B48: Exit EV/EBITDA multiple (returns case) | D48: =Inputs!D43 | E48: =Inputs!E43 | F48: =Inputs!F43
B49: Discount rate — Year-10 DFV bridge | D49: =Inputs!D44 | E49: =Inputs!E44 | F49: =Inputs!F44
B50: Plus: yearly schedules (fleet additions, unit sales, programmes) and the acquisition on/off flags — see Inputs §G and the Acquisitions tab.

Sheet Outputs
B2: Outputs — deck & memo tie-out
B3: Every figure quoted in the deck or memo, with the slide/section that uses it. Live under the selected scenario.
B6: Figure | C6: Value | D6: Unit | E6: Used on
B7: Active scenario | C7: =Inputs!C7 | E7: All
B8: Revenue Y0 (2026) | C8: ='P&L & Capital'!D12 | D8: USD M | E8: Memo §3
B9: Revenue Y2 (2028) | C9: ='P&L & Capital'!F12 | D9: USD M | E9: Deck — Revenue build
B10: Revenue Y4 (2030) | C10: ='P&L & Capital'!H12 | D10: USD M | E10: Deck — Revenue build
B11: Revenue Y5 (2031) | C11: ='P&L & Capital'!I12 | D11: USD M | E11: Deck — Revenue build, Market (SOM)
B12: Revenue Y6 (2032) | C12: ='P&L & Capital'!J12 | D12: USD M | E12: Deck — Revenue build
B13: Revenue Y7 (2033) | C13: ='P&L & Capital'!K12 | D13: USD M | E13: Deck — Returns
B14: Revenue Y8 (2034) | C14: ='P&L & Capital'!L12 | D14: USD M | E14: Deck — Revenue build
B15: Revenue Y10 (2036) | C15: ='P&L & Capital'!N12 | D15: USD M | E15: Deck — Revenue build, Bridge
B16: Organic revenue Y10 | C16: ='P&L & Capital'!N10 | D16: USD M | E16: Deck — Revenue build
B17: Acquired revenue Y10 | C17: ='P&L & Capital'!N11 | D17: USD M | E17: Deck — Revenue build
B18: Acquired share of revenue Y10 | C18: ='P&L & Capital'!N14 | D18: % | E18: Deck — Revenue build
B19: Adjusted EBITDA Y5 | C19: ='P&L & Capital'!I23 | D19: USD M | E19: Deck — Financial summary
B20: Adjusted EBITDA Y7 | C20: ='P&L & Capital'!K23 | D20: USD M | E20: Deck — Returns
B21: Adjusted EBITDA Y10 | C21: ='P&L & Capital'!N23 | D21: USD M | E21: Deck — Bridge
B22: Adjusted EBITDA margin Y5 | C22: ='P&L & Capital'!I24 | D22: % | E22: Deck — Financial summary
B23: Adjusted EBITDA margin Y10 | C23: ='P&L & Capital'!N24 | D23: % | E23: Deck — Bridge
B24: Acquisitions in plan (count) | C24: =Acquisitions!H15 | D24: count | E24: Deck — Roadmap, Revenue build
B25: Total acquisition consideration (live basis) | C25: =Acquisitions!I14 | D25: USD M | E25: Deck — Capital
B26: Total consideration at 2.0x-revenue stress | C26: =Acquisitions!K14 | D26: USD M | E26: Deck — Capital, Memo
B27: Total entry revenue acquired | C27: =Acquisitions!E14 | D27: USD M | E27: Memo
B28: Blended price / entry revenue | C28: =Acquisitions!I16 | D28: x | E28: Memo
B29: Capital required — Phase 1 (2026–27) | C29: ='P&L & Capital'!D40 | D29: USD M | E29: Deck — Capital
B30: Capital required — Phase 2 (2028–29) | C30: ='P&L & Capital'!D41 | D30: USD M | E30: Deck — Capital
B31: Capital required — Phase 3 (2030–31) | C31: ='P&L & Capital'!D42 | D31: USD M | E31: Deck — Capital
B32: Capital required — 2032–36 | C32: ='P&L & Capital'!D43 | D32: USD M | E32: Deck — Capital
B33: Total equity funding drawn 2026–36 | C33: ='P&L & Capital'!D44 | D33: USD M | E33: Deck — Capital, Returns
B34: Peak cumulative funding requirement | C34: ='P&L & Capital'!D47 | D34: USD M | E34: Memo
B35: Gross use 2026–36: acquisition consideration | C35: =-SUM('P&L & Capital'!D31:N31) | D35: USD M | E35: Deck — Capital
B36: Gross use 2026–36: integration costs | C36: =-SUM('P&L & Capital'!D21:N21) | D36: USD M | E36: Deck — Capital
B37: Gross use 2026–36: fleet & maintenance capex | C37: =-SUM('P&L & Capital'!D28:N28)-SUM('P&L & Capital'!D29:N29) | D37: USD M | E37: Deck — Capital
B38: Gross use 2026–36: development & partnership programmes | C38: =-SUM('P&L & Capital'!D20:N20) | D38: USD M | E38: Deck — Capital
B39: Gross use 2026–36: working capital | C39: =-SUM('P&L & Capital'!D30:N30) | D39: USD M | E39: Deck — Capital
B40: Gross use: corporate platform cost 2026–28 | C40: =-SUM('P&L & Capital'!D19:F19) | D40: USD M | E40: Deck — Capital
B41: Initial raise (Round 1) — amount | C41: =Inputs!$C$50 | D41: USD M | E41: Deck — The Ask
B42: Initial raise — Phase 1 portion (fully funds Phase 1) | C42: ='P&L & Capital'!D40 | D42: USD M | E42: Deck — The Ask
B43: Initial raise — reserve toward first-acquisition diligence & working capital | C43: =Inputs!$C$50-'P&L & Capital'!D40 | D43: USD M | E43: Deck — The Ask
B44: Initial raise as % of full Phase 1+2 requirement | C44: =Inputs!$C$50/('P&L & Capital'!D40+'P&L & Capital'!D41) | D44: % | E44: Deck — The Ask
B45: First acquisition (Large-calibre & artillery) — consideration at entry | C45: =Acquisitions!I7 | D45: USD M | E45: Deck — The Ask, De-risking
B46: Second acquisition (Metals recovery) — consideration at entry | C46: =Acquisitions!I8 | D46: USD M | E46: Deck — The Ask, De-risking
B47: First two acquisitions — combined consideration | C47: =Acquisitions!I7+Acquisitions!I8 | D47: USD M | E47: Deck — The Ask, De-risking
B48: eMACS units in service Y5 | C48: ='Organic Build'!I11 | D48: count | E48: Memo
B49: eMACS units in service Y10 | C49: ='Organic Build'!N11 | D49: count | E49: Memo
B50: Total FTE Y5 | C50: =Headcount!I16 | D50: FTE | E50: Deck — Financial summary
B51: Total FTE Y10 | C51: =Headcount!N16 | D51: FTE | E51: Deck — Revenue build
B52: TAM 2026 (forming annual) | C52: =Market!E15 | D52: USD M | E52: Deck — Market
B53: TAM blended growth | C53: =Market!F15 | D53: % | E53: Deck — Market
B54: Episodic layer — Ukraine EHM need 2026–35 | C54: =Market!C16 | D54: USD M | E54: Deck — Market
B55: SAM 2026 | C55: =Market!E22 | D55: USD M | E55: Deck — Market
B56: SAM Year 5 | C56: =Market!E25 | D56: USD M | E56: Deck — Market
B57: SAM Year 10 | C57: =Market!E26 | D57: USD M | E57: Deck — Market
B58: Share of SAM Year 5 | C58: =Market!E30 | D58: % | E58: Deck — Market
B59: Share of SAM Year 10 | C59: =Market!E32 | D59: % | E59: Deck — Revenue build
B60: Exit multiple (returns case) | C60: =Inputs!$C$43 | D60: x | E60: Deck — Returns
B61: MOIC — exit Year 5 | C61: ='Returns & Valuation'!C19 | D61: x | E61: Deck — Returns
B62: IRR — exit Year 5 | C62: ='Returns & Valuation'!C18 | D62: % | E62: Deck — Returns
B63: MOIC — exit Year 7 | C63: ='Returns & Valuation'!C23 | D63: x | E63: Deck — Returns
B64: IRR — exit Year 7 | C64: ='Returns & Valuation'!C22 | D64: % | E64: Deck — Returns
B65: MOIC — exit Year 10 | C65: ='Returns & Valuation'!C27 | D65: x | E65: Memo
B66: IRR — exit Year 10 | C66: ='Returns & Valuation'!C26 | D66: % | E66: Memo
B67: Enterprise value at Year-7 exit | C67: ='Returns & Valuation'!K11 | D67: USD M | E67: Deck — Returns
B68: DFV bridge — low multiple | C68: =Inputs!$C$45 | D68: x | E68: Deck — Bridge
B69: DFV bridge — high multiple | C69: =Inputs!$C$46 | D69: x | E69: Deck — Bridge
B70: Future firm value — low | C70: ='Returns & Valuation'!C40 | D70: USD M | E70: Deck — Bridge
B71: Future firm value — high | C71: ='Returns & Valuation'!C41 | D71: USD M | E71: Deck — Bridge
B72: Discount rate | C72: =Inputs!$C$44 | D72: % | E72: Deck — Bridge
B73: Discounted firm value — midpoint | C73: ='Returns & Valuation'!C46 | D73: USD M | E73: Deck — Bridge
B74: Discounted value net of capital deployed | C74: ='Returns & Valuation'!C48 | D74: USD M | E74: Deck — Bridge
B75: Sensitivity: 20% / 5 periods (mismatched) | C75: ='Returns & Valuation'!D52 | D75: USD M | E75: Deck — Bridge
B76: Sensitivity: 30% / 10 periods | C76: ='Returns & Valuation'!F54 | D76: USD M | E76: Deck — Bridge
B77: FY2025 combined revenue (USD M, actual) | C77: =Baseline!F20 | D77: USD M | E77: Memo §2
B78: FY2025 combined EBITDA (USD M, actual) | C78: =Baseline!F21 | D78: USD M | E78: Memo §2

Sheet Sources
B2: Sources
B3: Every sourced figure in the model, deck and memo. Company-provided items are marked as such.
B6: Figure | C6: Status | D6: Source / URL | E6: Date
B7: M1 · World military expenditure 2025 = US$2,887bn, all-time record, 11th consecutive rise | C7: VERIFIED | D7: SIPRI, Trends in World Military Expenditure 2025 — https://www.sipri.org/sites/default/files/2026-04/2604_milex_2025.pdf | E7: Apr 2026
B8: M2 · European military spending doubled 2016–25 (+102%); Europe $864bn in 2025 | C8: VERIFIED | D8: SIPRI, Trends in World Military Expenditure 2025 — https://www.sipri.org/sites/default/files/2026-04/2604_milex_2025.pdf | E8: Apr 2026
B9: M3 · 65 state-based armed conflicts in 2025 — most since records began in 1946; 8 interstate | C9: VERIFIED | D9: Uppsala University / UCDP press release — https://www.uu.se/en/press/press-releases/2026/2026-06-09-ucdp-record-number-of-conflicts-between-states | E9: 9 Jun 2026
B10: M4 · Global mine action funding US$1.07bn in 2024 (international $761M, national $306.3M); US freeze in 2025 cut programmes | C10: VERIFIED | D10: Landmine Monitor 2025 — https://the-monitor.org/api/assets/reports/Landmine-Monitors/LMM2025/Downloads/LM2025-Major-Findings_EN.pdf | E10: Nov 2025
B11: M5 · Ukraine explosive-hazard management need US$27.6bn (2026–2035); ~133,000 km² contaminated | C11: VERIFIED (SUPERSEDES RDNA4) | D11: World Bank / Govt of Ukraine, RDNA5 — https://www.worldbank.org/en/news/press-release/2026/02/23/updated-ukraine-recovery-and-reconstruction-needs-assessment-released | E11: 23 Feb 2026
B12: M6 · Global EOD equipment & services market ~US$8.5–8.8bn (2025–26), ~3% CAGR; equipment-only estimates ~$5.5–5.7bn | C12: PARTIALLY VERIFIED | D12: Global Growth Insights, EOD market report — https://www.globalgrowthinsights.com/market-reports/explosive-ordnance-disposal-eod-market-109006 | E12: 2026
B13: M7 · US conventional weapons destruction assistance >US$5.09bn to 125+ countries since 1993 | C13: VERIFIED (SUPERSEDES '$4bn') | D13: US Dept of State / JMU CISR mirror — https://www.jmu.edu/cisr/research/tweis/fy23/index.shtml | E13: Apr 2024
B14: M8 · Rheinmetall 155mm capacity target 'at least 1.1 million' (company release) to 'up to 1.5 million' rounds/yr by 2027 (company statements reported by press) | C14: PARTIALLY VERIFIED | D14: Rheinmetall AG press release — https://www.rheinmetall.com/en/media/news-watch/news/2025/06/2025-06-03-rheinmetall-receives-major-international-orders-for-155mm-artillery-ammunition | E14: Jun 2025
B15: M9 · US Army 155mm target 100,000 rounds/month (Oct 2025 goal); ~36,000/month actual per DoD IG (Jul 2026) | C15: VERIFIED | D15: Stars and Stripes — https://www.stripes.com/branches/army/2026-07-14/army-artillery-shell-shortfall-22262070.html | E15: 14 Jul 2026
B16: M10 · NATO: up to $145bn in shared munitions and air-defence requirements identified; Allied production up ~sixfold | C16: VERIFIED | D16: Breaking Defense — https://breakingdefense.com/2026/03/nato-sees-145b-in-munitions-needs-as-members-all-hit-2-percent-gdp-for-first-time/ | E16: 26 Mar 2026
B17: D1 · US demil stockpile 296,534 tons as of 4 Dec 2025 (246,681 conventional + 49,853 missile components) — B5A account | C17: VERIFIED | D17: US Army FY2027 Budget Estimates, Procurement of Ammunition — https://www.asafm.army.mil/Portals/72/Documents/BudgetMaterial/2027/Discretionary%20Budget/Procurement/Procurement_of_Ammunition.pdf | E17: Apr 2026
... B75: R3 · Team slide: Tom (Founder & CEO, TWB Designs) and Joe Kasper (Strategic Advisor) | C75: COMPANY-PROVIDED | D75: REalloys, Inc. — https://realloys.com/team/ | E75: 30 Mar 2026

Sheet Fact-Check Log
B2: Fact-check log & source map
B3: Every key claim in the deck and memo: status, support found, and what changed versus the August 2026 package. Also lists the changes made to the deck.
B6: ID | C6: Area | D6: Claim as used in the new package | E6: Status | F6: Support found | G6: Source (hyperlinked) | H6: Date | I6: Change vs August 2026 package
B7: M1 | C7: Market | D7: World military expenditure 2025 = US$2,887bn, all-time record, 11th consecutive rise | E7: VERIFIED | F7: SIPRI Fact Sheet Apr 2026: 'rose by 2.9 per cent in real terms to $2887 billion in 2025… highest spending level ever recorded' | G7: SIPRI, Trends in World Military Expenditure 2025 | H7: Apr 2026 | I7: New in package (not in original deck)
B8: M2 | C8: Market | D8: European military spending doubled 2016–25 (+102%); Europe $864bn in 2025 | E8: VERIFIED | F8: Same SIPRI fact sheet: 'Over the decade 2016–25, military spending in the region doubled (+102 per cent)' | G8: SIPRI, Trends in World Military Expenditure 2025 | H8: Apr 2026 | I8: New
B9: M3 | C9: Market | D9: 65 state-based armed conflicts in 2025 — most since records began in 1946; 8 interstate | E9: VERIFIED | F9: Davies, Pettersson & Öberg (2026), 'Organized violence 1989–2025', Journal of Peace Research 63(4) | G9: Uppsala University / UCDP press release | H9: 9 Jun 2026 | I9: New
B10: M4 | C10: Market | D10: Global mine action funding US$1.07bn in 2024 (international $761M, national $306.3M); US freeze in 2025 cut programmes | E10: VERIFIED | F10: Landmine Monitor 2025 Major Findings; ICBL-CMC factsheet on 2025 US funding cuts | G10: Landmine Monitor 2025 | H10: Nov 2025 | I10: Retained from original model; year-tagged
B11: M5 | C11: Market | D11: Ukraine explosive-hazard management need US$27.6bn (2026–2035); ~133,000 km² contaminated | E11: VERIFIED (SUPERSEDES RDNA4) | F11: RDNA5 (23 Feb 2026): 'Total recovery and reconstruction needs are estimated at US$27.6 billion'; footprint reduced to ~133,000 km². Original package used RDNA4 $29.8bn / 139,000 km². | G11: World Bank / Govt of Ukraine, RDNA5 | H11: 23 Feb 2026 | I11: UPDATED: $29.8–31bn → $27.6bn (RDNA5)
B12: M6 | C12: Market | D12: Global EOD equipment & services market ~US$8.5–8.8bn (2025–26), ~3% CAGR; equipment-only estimates ~$5.5–5.7bn | E12: PARTIALLY VERIFIED | F12: Global Growth Insights: $8.55bn (2025) → $11.52bn (2035), 3.03% CAGR; Spherical Insights $8.61bn (2026); Mordor $5.69bn equipment (2025). The original deck's '$9.6bn' could not be found. | G12: Global Growth Insights, EOD market report | H12: 2026 | I12: SOFTENED: $9.0bn midpoint → $8.55bn with named house; CAGR 4.5% → 3.0%
B13: M7 | C13: Market | D13: US conventional weapons destruction assistance >US$5.09bn to 125+ countries since 1993 | E13: VERIFIED (SUPERSEDES '$4bn') | F13: To Walk the Earth in Safety, 23rd ed. (FY2023): 'more than $5.09 billion in assistance to over 125 countries and areas since 1993' | G13: US Dept of State / JMU CISR mirror | H13: Apr 2024 | I13: UPDATED: $4bn/100+ → $5.09bn/125+
B14: M8 | C14: Market | D14: Rheinmetall 155mm capacity target 'at least 1.1 million' (company release) to 'up to 1.5 million' rounds/yr by 2027 (company statements reported by press) | E14: PARTIALLY VERIFIED | F14: Rheinmetall press release Jun 2025 (1.1M); Kyiv Post Oct 2025 (up to 1.5M) | G14: Rheinmetall AG press release | H14: Jun 2025 | I14: SOFTENED: '1.5M' → '1.1–1.5M (company statements)'
B15: M9 | C15: Market | D15: US Army 155mm target 100,000 rounds/month (Oct 2025 goal); ~36,000/month actual per DoD IG (Jul 2026) | E15: VERIFIED | F15: DoD IG evaluation reported by Stars and Stripes 14 Jul 2026 | G15: Stars and Stripes | H15: 14 Jul 2026 | I15: New (used as production-surge context only)
B16: M10 | C16: Market | D16: NATO: up to $145bn in shared munitions and air-defence requirements identified; Allied production up ~sixfold | E16: VERIFIED | F16: NATO Annual Report 2025 briefing (26 Mar 2026), Rutte remarks | G16: Breaking Defense | H16: 26 Mar 2026 | I16: New
B17: D1 | C17: US demil | D17: US demil stockpile 296,534 tons as of 4 Dec 2025 (246,681 conventional + 49,853 missile components) — B5A account | E17: VERIFIED | F17: FY2027 Army Procurement of Ammunition justification book, line 4099EP1700 | G17: US Army FY2027 Budget Estimates, Procurement of Ammunition | H17: Apr 2026 | I17: REPLACES original deck's implied '400,000 tons' framing
... B89: X10 | C89: Deck change | D89: Slide 7 (Team) redesign: subheading line removed under each member's name; photo/initials image and card enlarged for both Tom and Joe Kasper; Kasper's credential line folded into the first bullet point instead of a standalone subheading | E89: CHANGE | F89: Tom, 3 Sep 2026: "On slide 7, Remove the subheading and increase the size of the box and image for each member." | G89: - | H89: 3 Sep 2026 | I89: Layout only - no factual claim changed; same sourced content as R3/R4 (Kasper bio) retained in the enlarged bullet list
